Workbook

Sheet Initial Investment & Cashflows
A2: Project 1:
A3: Beyondfeel Running Shoes 2026
A6: Initial investment
A7: Cost of building:
A8: 210000000
A9: +
A10: Net Working Capital: | K10: Operating cashflow
A11: 0 | K11: 14500000-(14500000*43%_
A12: 0 (R&d sunk cost)
A13: +
A14: 0 interest
A15: Total initial investment= | B15: 210000000
A20: Operating cashflow
A22: Revenue
A24: revune per pair of shoes sold = $198
A25: Net revenue per pair of shoes= $114
A26: Total revenue =pairs sold x total revenue per pair
A27: Net revenue = pairs sold x net revenue per pair
A28: Net adjusted revenue = net revenue - lost sales
A30: Year | B30: Pairs sold | C30: Total revenue per pair | D30: Total revenue | E30: Net revenue per pair | F30: Net revenue | G30: Lost sales | H30: adjusted Revenue
A31: 2026 | B31: 1450000 | C31: 198 | D31: =B31*C31 -> 287100000 | E31: 114 | F31: =B31*E31 -> 165300000 | G31: 22000000 | H31: =F31-G31 -> 143300000
A32: 2027 | B32: 1920000 | C32: 198 | D32: =B32*C32 -> 380160000 | E32: 114 | F32: =B32*E32 -> 218880000 | G32: 12000000 | H32: =F32-G32 -> 206880000
A33: 2028 | B33: 2100000 | C33: 198 | D33: =B33*C33 -> 415800000 | E33: 114 | F33: =B33*E33 -> 239400000 | H33: =F33-G33 -> 239400000
A34: 2029 | B34: 2850000 | C34: 198 | D34: =B34*C34 -> 564300000 | E34: 114 | F34: =B34*E34 -> 324900000 | H34: =F34-G34 -> 324900000
A35: 2030 | B35: 2300000 | C35: 198 | D35: =B35*C35 -> 455400000 | E35: 114 | F35: =B35*E35 -> 262200000 | H35: =F35-G35 -> 262200000
A36: 2031 | B36: 1250000 | C36: 198 | D36: =B36*C36 -> 247500000 | E36: 114 | F36: =B36*E36 -> 142500000 | H36: =F36-G36 -> 142500000
A37: Total | B37: =SUM(B31:B36) -> 11870000 | D37: =SUM(D31:D36) -> 2350260000 | F37: =SUM(F31:F36) -> 1353180000 | G37: =SUM(G31:G32) -> 34000000 | H37: =SUM(H31:H36) -> 1319180000
A40: Varible cost:
A42: variable cost = adjusted revenue x percentage
A43: Varible cost = 43% of net revenue
A45: Year | B45: Net revenue | C45: percentage | D45: Variable cost
A46: 2026 | B46: =B31*E31 -> 165300000 | C46: 0.43 | D46: =B46*C46 -> 71079000
A47: 2027 | B47: =B32*E32 -> 218880000 | C47: 0.43 | D47: =B47*C47 -> 94118400
A48: 2028 | B48: =B33*E33-G33 -> 239400000 | C48: 0.43 | D48: =B48*C48 -> 102942000
A49: 2029 | B49: =B34*E34-G34 -> 324900000 | C49: 0.43 | D49: =B49*C49 -> 139707000
A50: 2030 | B50: =B35*E35-G35 -> 262200000 | C50: 0.43 | D50: =B50*C50 -> 112746000
A51: 2031 | B51: =B36*E36-G36 -> 142500000 | C51: 0.43 | D51: =B51*C51 -> 61275000
A52: Total | B52: =SUM(B46:B51) -> 1353180000 | D52: =SUM(D46:D51) -> 581867400
A55: Fixed cost:
A57: Year | B57: Selling, general and other administrative expenses | C57: Athlete Endorsment | D57: other advertising and promotion cost | E57: Total Fixed cost
A58: 2026 | B58: 12000000 | C58: 6000000 | D58: 32000000 | E58: =B58+C58+D58 -> 50000000
A59: 2027 | B59: 12000000 | C59: 6000000 | D59: 24000000 | E59: =B59+C59+D59 -> 42000000
A60: 2028 | B60: 12000000 | C60: 6000000 | D60: 20000000 | E60: =B60+C60+D60 -> 38000000
A61: 2029 | B61: 12000000 | C61: 6000000 | D61: 30000000 | E61: =B61+C61+D61 -> 48000000
A62: 2030 | B62: 12000000 | C62: 6000000 | D62: 25000000 | E62: =B62+C62+D62 -> 43000000
A63: 2031 | B63: 12000000 | C63: 6000000 | D63: 18000000 | E63: =B63+C63+D63 -> 36000000
A64: Total | B64: =SUM(B58:B63) -> 72000000 | C64: =SUM(C58:C63) -> 36000000 | D64: =SUM(D58:D63) -> 149000000 | E64: =SUM(E58:E63) -> 257000000
A68: Depreciation:
A69: Depreciation = perchase price x depreciation rate
A71: Year | B71: Purchase price | C71: Depreciation Rate % | D71: Depreciation
A72: 2026 | B72: 210000000 | C72: 0.026 | D72: =B72*C72 -> 5460000
A73: 2027 | B73: 210000000 | C73: 0.05 | D73: =B73*C73 -> 10500000
A74: 2028 | B74: 210000000 | C74: 0.047 | D74: =B74*C74 -> 9870000
A75: 2029 | B75: 210000000 | C75: 0.045 | D75: =B75*C75 -> 9450000
A76: 2030 | B76: 210000000 | C76: 0.043 | D76: =B76*C76 -> 9030000
A77: 2031 | B77: 210000000 | C77: 0.04 | D77: =B77*C77 -> 8400000
A78: Accumulated | B78: 210000000 | C78: =SUM(C72:C77) -> 0.251 | D78: =SUM(D72:D77) -> 52710000
A82: Total Cost
A84: Total Cost = Total Variable Cost + Total Fixed Cost
A86: Year | B86: Fixed cost | C86: Variable cost | D86: Total Cost
A87: 2026 | B87: =B58+C58+D58 -> 50000000 | C87: =B46*C46 -> 71079000 | D87: =B87+C87 -> 121079000
A88: 2027 | B88: =B59+C59+D59 -> 42000000 | C88: =B47*C47 -> 94118400 | D88: =B88+C88 -> 136118400
A89: 2028 | B89: =B60+C60+D60 -> 38000000 | C89: =B48*C48 -> 102942000 | D89: =B89+C89 -> 140942000
A90: 2029 | B90: =B61+C61+D61 -> 48000000 | C90: =B49*C49 -> 139707000 | D90: =B90+C90 -> 187707000
A91: 2030 | B91: =B62+C62+D62 -> 43000000 | C91: =B50*C50 -> 112746000 | D91: =B91+C91 -> 155746000
A92: 2031 | B92: =B63+C63+D63 -> 36000000 | C92: =B51*C51 -> 61275000 | D92: =B92+C92 -> 97275000
A93: Total | B93: =SUM(B87:B92) -> 257000000 | C93: =SUM(C87:C92) -> 581867400 | D93: =SUM(D87:D92) -> 838867400
A97: Earning Before Interest and Tax (EBIT)
A99: EBIT = Adjusted Revenue - (Total Cost + Depreciation)
B101: 2026 | C101: 2027 | D101: 2028 | E101: 2029 | F101: 2030 | G101: 2031
A102: Adjusted Revenue | B102: =F31-G31 -> 143300000 | C102: =F32-G32 -> 206880000 | D102: =F33-G33 -> 239400000 | E102: =F34-G34 -> 324900000 | F102: =F35-G35 -> 262200000 | G102: =F36-G36 -> 142500000
A103: Total Cost | B103: =B87+C87 -> 121079000 | C103: =B88+C88 -> 136118400 | D103: =B89+C89 -> 140942000 | E103: =B90+C90 -> 187707000 | F103: =B91+C91 -> 155746000 | G103: =B92+C92 -> 97275000
A104: Depreciation | B104: =B72*C72 -> 5460000 | C104: =B73*C73 -> 10500000 | D104: =B74*C74 -> 9870000 | E104: =B75*C75 -> 9450000 | F104: =B76*C76 -> 9030000 | G104: =B77*C77 -> 8400000
A105: EBIT | B105: =B102-(B103+B104) -> 16761000 | C105: =C102-(C103+C104) -> 60261600 | D105: =D102-(D103+D104) -> 88588000 | E105: =E102-(E103+E104) -> 127743000 | F105: =F102-(F103+F104) -> 97424000 | G105: =G102-(G103+G104) -> 36825000
A108: Net Income
A110: Tax= EBIT x Tax Rate
A111: Net Income = EBIT - Tax
B113: 2026 | C113: 2027 | D113: 2028 | E113: 2029 | F113: 2030 | G113: 2031
A114: EBIT | B114: =B102-(B103+B104) -> 16761000 | C114: =C102-(C103+C104) -> 60261600 | D114: =D102-(D103+D104) -> 88588000 | E114: =E102-(E103+E104) -> 127743000 | F114: =F102-(F103+F104) -> 97424000 | G114: =G102-(G103+G104) -> 36825000
A115: Tax | B115: =B114*21% -> 3519810 | C115: =C114*21% -> 12654936 | D115: =D114*21% -> 18603480 | E115: =E114*21% -> 26826030 | F115: =F114*21% -> 20459040 | G115: =G114*21% -> 7733250
A116: Net Income | B116: =B114-B115 -> 13241190 | C116: =C114-C115 -> 47606664 | D116: =D114-D115 -> 69984520 | E116: =E114-E115 -> 100916970 | F116: =F114-F115 -> 76964960 | G116: =G114-G115 -> 29091750
A119: Operating Cash flow
A121: operating cashflow = net income + depreciation
A123: Year | B123: Net Income | C123: Depreciation | D123: Operating cashflow
A124: 2026 | B124: =B114-B115 -> 13241190 | C124: =B72*C72 -> 5460000 | D124: =B124+C124 -> 18701190
A125: 2027 | B125: =C114-C115 -> 47606664 | C125: =B73*C73 -> 10500000 | D125: =B125+C125 -> 58106664
A126: 2028 | B126: =D114-D115 -> 69984520 | C126: =B74*C74 -> 9870000 | D126: =B126+C126 -> 79854520
A127: 2029 | B127: =E114-E115 -> 100916970 | C127: =B75*C75 -> 9450000 | D127: =B127+C127 -> 110366970
A128: 2030 | B128: =F114-F115 -> 76964960 | C128: =B76*C76 -> 9030000 | D128: =B128+C128 -> 85994960
A129: 2031 | B129: =G114-G115 -> 29091750 | C129: =B77*C77 -> 8400000 | D129: =B129+C129 -> 37491750
A134: Terminal cashflow:
A136: Accumulated depreciation for factory =$52,710,000
A137: Bookvalue of buildng/factory=purchise price - accumulated depreciation | B137: Bookvalue of building/factory=$210,000,000 - $52,710,000 =$157,290,000
A138: Proceeds from sale of building/factory=$125,000,000
A139: capital gain or loss on sale of building/factory=proceeds from sales -bookvalue | B139: capital gain or loss on sale of building/factory=$125,000,000 -$157,290,000= -$32,290,000 (loss)
A140: Tax Rate = 21%
A141: Tax Rebate on Sale of building/factory = Capital loss x Tax Rate | B141: Tax Rebate on Sale of building/factory =$32,290,000 x 21% = $6,780,900
A142: Change in networking Capital = $0
A143: Terminal cashflow = proceeds from sale + Tax Rebate + Change in networking capital | B143: Terminal cashflow = $125,000,000 + $6,780,900 + 0 = $131,780,900
A144: Terminal Cashflow = | B144: 131780900
...

Sheet Capital budgeting
A1: Project 1:
A2: Running Shoes 2026
A4: Payback Period Method:
A6: Year | B6: Cash Flow | C6: Accumulated Cashflow
A7: 0 | B7: -210000000
A8: 2026 | B8: ='Initial Investment & Cashflows'!B150 -> 18701190 | C8: =C7+B8 -> 18701190
A9: 2027 | B9: ='Initial Investment & Cashflows'!B151 -> 58106664 | C9: =C8+B9 -> 76807854
A10: 2028 | B10: ='Initial Investment & Cashflows'!B152 -> 79854520 | C10: =C9+B10 -> 156662374
A11: 2029 | B11: ='Initial Investment & Cashflows'!B153 -> 110366970 | C11: =C10+B11 -> 267029344
A12: 2030 | B12: ='Initial Investment & Cashflows'!B154 -> 85994960 | C12: =C11+B12 -> 353024304
A13: 2031 | B13: ='Initial Investment & Cashflows'!B155 -> 169272650 | C13: =C12+B13 -> 522296954
A15: Payback period =(210,000,000-156,662,374/110,366,970 +3 years= | B15: =((210000000-C10)/B11)+3 -> 3.4832753
A17: Payback period =3.48 years
A20: The discounted payback:
A21: Discounted payback= | B21: undiscounted cash flow* (1-discount rate)^number of years
A22: Discount Rate= | B22: 0.1
B24: Cash Flow | D24: Accumulated Cash Flow
A25: Year | B25: Undiscounted | C25: Discounted | D25: Undiscounted | E25: Discounted
A26: 2026 | B26: =B8 -> 18701190 | C26: =B26/(1+10%)^1 -> 17001082 | D26: =B26 -> 18701190 | E26: =C26 -> 17001082
A27: 2027 | B27: =B9 -> 58106664 | C27: =B27/(1+10%)^2 -> 48022036 | D27: =D26+B27 -> 76807854 | E27: =E26+C27 -> 65023118
A28: 2028 | B28: =B10 -> 79854520 | C28: =B28/(1+10%)^3 -> 59995883 | D28: =D27+B28 -> 156662374 | E28: =E27+C28 -> 1.25019e+08
A29: 2029 | B29: =B11 -> 110366970 | C29: =B29/(1+10%)^4 -> 75382126 | D29: =D28+B29 -> 267029344 | E29: =E28+C29 -> 2.0040113e+08
A30: 2030 | B30: =B12 -> 85994960 | C30: =B30/(1+10%)^5 -> 53396104 | D30: =D29+B30 -> 353024304 | E30: =E29+C30 -> 2.5379723e+08
A31: 2031 | B31: =B13 -> 169272650 | C31: =B31/(1+10%)^6 -> 95549998 | D31: =D30+B31 -> 522296954 | E31: =E30+C31 -> 3.4934723e+08
A35: Discounted Payback period= | B35: (210,000,000-200,401,126.51)/53,396,104.34 + 4 years
A36: Discounted Payback period= | B36: =((210000000-E29)/C30)+4 -> 4.1797673 | C36: 4.18 Years
A40: Net Present Value (NPV):
A41: Accumulated cashflows = | B41: =E31 -> 3.4934723e+08
A42: initial investment= | B42: 210000000
A44: NPV = Present value of Accumulated cashflows - initial investment= | B44: 349,347,228.85- $210,000,000
A45: NPV = | B45: =E31-B42 -> 1.3934723e+08 | C45: Postive NPV
A48: Profitibility Index:
A49: Accumulated cashflows = | B49: =B41 -> 3.4934723e+08
A50: Initial investment= | B50: =B42 -> 210000000
A51: Profitibility index= Present value of cash flows/ Initial investment | B51: 275,254,943.98/210,000,000
A52: Profitability Index = | B52: =B49/B50 -> 1.6635582
A55: Internal Rate Of Return (IRR):
A56: Initial investment= | B56: =B50 -> 210000000
A57: NPV (0) = -Initial Investment + Present Value of Cashflows /(1+IRR)^n
A58: IRR = | B58: =IRR(B7:B13) -> 0.25124355
A69: Project 2:
A70: Trail & Tavel 2026
A72: Payback Period Method:
A74: Year | B74: Cash Flow | C74: Accumulated Cashflow
A75: 0 | B75: -90000000
A76: 2026 | B76: ='Initial Investment & Cashflows'!B293 -> 19708150 | C76: =C75+B76 -> 19708150
A77: 2027 | B77: ='Initial Investment & Cashflows'!B294 -> 32251761 | C77: =C76+B77 -> 51959910
A78: 2028 | B78: ='Initial Investment & Cashflows'!B295 -> 65585695 | C78: =C77+B78 -> 1.1754561e+08
A80: Payback period =(90,000,000-51,959,910.40/65,585,694.69 +2 years= | B80: =((90000000-C77)/B78)+2 -> 2.5800059
A82: Payback period =2.58 years
A85: The discounted payback:
A86: Discounted payback= | B86: undiscounted cash flow* (1-discount rate)^number of years
B88: Cash Flow | D88: Accumulated Cash Flow
A89: Year | B89: Undiscounted | C89: Discounted | D89: Undiscounted | E89: Discounted
A90: 2026 | B90: ='Initial Investment & Cashflows'!B293 -> 19708150 | C90: =B90/(1+12%)^1 -> 17596562 | D90: =B90 -> 19708150 | E90: =C90 -> 17596562
A91: 2027 | B91: ='Initial Investment & Cashflows'!B294 -> 32251761 | C91: =B91/(1+12%)^2 -> 25710906 | D91: =D90+B91 -> 51959910 | E91: =E90+C91 -> 43307468
A92: 2028 | B92: ='Initial Investment & Cashflows'!B295 -> 65585695 | C92: =B92/(1+12%)^3 -> 46682602 | D92: =D91+B92 -> 1.1754561e+08 | E92: =E91+C92 -> 89990070
A94: Discounted Payback period= | B94: (90,000,000-43,307,468.38)/46,682,602.02 + 2 years
A95: Discounted Payback period= | B95: =((90000000-E91)/C92)+2 -> 3.0002127 | C95: 3 years
A98: Net Present Value (NPV):
A99: Accumulated cashflows = | B99: =E92 -> 89990070
A100: initial investment= | B100: 90000000
A102: NPV = Present value of Accumulated cashflows - initial investment= | B102: 89,990,070.40- $90,000,000
A103: NPV = | B103: =B99-B100 -> -9929.6003 | C103: negative NPV
A106: Profitibility Index:
A107: Accumulated cashflows = | B107: =E92 -> 89990070
A108: initial investment= | B108: 90000000
A109: Profitibility index= Present value of cash flows/ Initial investment | B109: 89,990,070.40/210000000
A110: Profitability Index = | B110: =B107/B108 -> 0.99988967
A113: Internal Rate Of Return (IRR):
A114: Initial investment= | B114: =B108 -> 90000000
A115: NPV (0) = -Initial Investment + Present Value of Cashflows /(1+IRR)^n
A116: IRR = | B116: =IRR(B75:B78) -> 0.11994681

Sheet WACC
A1: WEIGHTED AVERAGE COST OF CAPITAL
A3: OVERALL COMPANY WACC:
A4: WACC = E/V x Re + D/V x Rd x (1-Tc) | B4: =B8*B10+B9*B14*(1-B17) -> 0.088447619
A5: Firm Value V = Total Equity E + Total Debt D | B5: 21840000000
A6: Total Equity E = | B6: 20080000000
A7: Total Debt D = | B7: 1760000000
A8: Equity weight (E/V) = | B8: =B6/B5 -> 0.91941392
A9: Debt weight (D/V) = | B9: =B7/B5 -> 0.080586081
A10: Cost of Equity Re (CAPM) = Rf + Be x (Rm - Rf) | B10: =B11+B12*(B13) -> 0.0962
A11: Risk Free (Rf) = | B11: 0.0401
A12: Beta (Be) = | B12: 1.02
A13: Market Risk Premium (Rm - Rf) = | B13: 0.055
A14: Cost of Debt Rd = Interst expense/ Total Debt | B14: =B15/B16 -> 0
A15: Interest expense = | B15: 0
A16: Total Debt = | B16: 1760000000
A17: Effective Tax Rate = | B17: 0.305
A21: Project 1 WACC:
A22: WACC = E/V x Re + D/V x Rd x (1-Tc) | B22: =B26*B28+B27*B32*(1-B35) -> 0.10330989
A23: Firm Value (Initial investment) V = Total Equity E + Total Debt D | B23: =B24+B25 -> 210000000
A24: Total Equity E = | B24: =B26*'Initial Investment & Cashflows'!B15 -> 1.9307692e+08
A25: Total Debt D = | B25: =B27*'Initial Investment & Cashflows'!B15 -> 16923077
A26: Equity weight (E/V) = | B26: =B8 -> 0.91941392
A27: Debt weight (D/V) = | B27: =B9 -> 0.080586081
A28: Cost of Equity Re (CAPM) = Rf + Be x (Rm - Rf) | B28: =B29+B30*(B31) -> 0.105
A29: Risk Free (Rf) = | B29: =B11 -> 0.0401
A30: Beta (Be) = | B30: 1.18
A31: Market Risk Premium (Rm - Rf) = | B31: =B13 -> 0.055
A32: Cost of Debt Rd = Interst expense/ Total Debt | B32: =B33/B34 -> 0.10636364
A33: Interest expense = | B33: 1800000
A34: Total Debt = | B34: =B25 -> 16923077
A35: Effective Tax Rate = | B35: 0.21
A39: Project 2 WACC:
A40: WACC = E/V x Re + D/V x Rd x (1-Tc) | B40: =B44*B46+B45*B50*(1-B53) -> 0.11721398
A41: Firm Value (Initial investment) V = Total Equity E + Total Debt D | B41: =B42+B43 -> 90000000
A42: Total Equity E = | B42: =B44*'Initial Investment & Cashflows'!B173 -> 82747253
A43: Total Debt D = | B43: =B45*'Initial Investment & Cashflows'!B173 -> 7252747.3
A44: Equity weight (E/V) = | B44: =B8 -> 0.91941392
A45: Debt weight (D/V) = | B45: =B9 -> 0.080586081
A46: Cost of Equity Re (CAPM) = Rf + Be x (Rm - Rf) | B46: =B47+B48*(B49) -> 0.11985
A47: Risk Free (Rf) = | B47: =B11 -> 0.0401
A48: Beta (Be) = | B48: 1.45
A49: Market Risk Premium (Rm - Rf) = | B49: =B13 -> 0.055
A50: Cost of Debt Rd = Interst expense/ Total Debt | B50: =B51/B52 -> 0.11030303
A51: Interest expense = | B51: 800000
A52: Total Debt = | B52: =B43 -> 7252747.3
A53: Effective Tax Rate = | B53: 0.21

Sheet ANPV
A1: Project 1: Beyonfeel Running Shoes 2026
A3: NPV = | B3: ='Capital budgeting'!B45 -> 1.3934723e+08 | D3: Year | E3: CashFlows | F3: Discounted CashFlows
A4: Number of Years (n) = | B4: 6 | D4: 0 | E4: -210000000
A5: Discount Rate = | B5: 0.1 | D5: 2026 | E5: ='Capital budgeting'!B8 -> 18701190 | F5: ='Capital budgeting'!C26 -> 17001082
A6: PVIFA = | B6: 4.355 | D6: 2027 | E6: ='Capital budgeting'!B9 -> 58106664 | F6: ='Capital budgeting'!C27 -> 48022036
D7: 2028 | E7: ='Capital budgeting'!B10 -> 79854520 | F7: ='Capital budgeting'!C28 -> 59995883
A8: ANPV = NPV/PVIFA | B8: 139,347,228.85/4.355 | D8: 2029 | E8: ='Capital budgeting'!B11 -> 110366970 | F8: ='Capital budgeting'!C29 -> 75382126
A9: ANPV = | B9: =B3/B6 -> 31997067 | D9: 2030 | E9: ='Capital budgeting'!B12 -> 85994960 | F9: ='Capital budgeting'!C30 -> 53396104
D10: 2031 | E10: ='Capital budgeting'!B13 -> 169272650 | F10: ='Capital budgeting'!C31 -> 95549998
A14: Project 2: Trail & Travel
A16: NPV = | B16: ='Capital budgeting'!B103 -> -9929.6003 | D16: Year | E16: CashFlows | F16: Discounted CashFlows
A17: Number of Years (n) = | B17: 3 | D17: 0 | E17: -90000000
A18: Discount Rate = | B18: 0.12 | D18: 2026 | E18: ='Capital budgeting'!B90 -> 19708150 | F18: ='Capital budgeting'!C90 -> 17596562
A19: PVIFA = | B19: 2.402 | D19: 2027 | E19: ='Capital budgeting'!B91 -> 32251761 | F19: ='Capital budgeting'!C91 -> 25710906
D20: 2028 | E20: ='Capital budgeting'!B92 -> 65585695 | F20: ='Capital budgeting'!C92 -> 46682602
A21: ANPV = NPV/PVIFA | B21: -9,929.60/2.402
A22: ANPV = | B22: =B16/B19 -> -4133.8885

Sheet sensitivity analysis
A1: Project 1:
A2: Beyondfeel Running Shoes 2026
A4: Year | B4: Cashflow
A5: 0 | B5: -210000000
A6: 2026 | B6: ='Initial Investment & Cashflows'!B150 -> 18701190
A7: 2027 | B7: ='Initial Investment & Cashflows'!B151 -> 58106664
A8: 2028 | B8: ='Initial Investment & Cashflows'!B152 -> 79854520
A9: 2029 | B9: ='Initial Investment & Cashflows'!B153 -> 110366970
A10: 2030 | B10: ='Initial Investment & Cashflows'!B154 -> 85994960
A11: 2031 | B11: ='Initial Investment & Cashflows'!B155 -> 169272650
A17: Discount Rate | B17: PV of Cash Flows | C17: NPV
A18: 0.0884 | B18: =NPV(A18,B6:B11) -> 3.649437e+08 | C18: =B5+B18 -> 1.549437e+08 | D18: WACC
A19: 0.1 | B19: =NPV(A19,B6:B11) -> 3.4934723e+08 | C19: =B5+B19 -> 1.3934723e+08 | D19: Given rate
A20: 0.11 | B20: =NPV(A20,B6:B11) -> 3.3663356e+08 | C20: =B5+B20 -> 1.2663356e+08
A21: 0.12 | B21: =NPV(A21,B6:B11) -> 3.2455348e+08 | C21: =B5+B21 -> 1.1455348e+08
A27: Project 2:
A28: Trail & Travel 2026
A30: Year | B30: Cash Flow
A31: 0 | B31: -90000000
A32: 2026 | B32: ='Initial Investment & Cashflows'!B293 -> 19708150
A33: 2027 | B33: ='Initial Investment & Cashflows'!B294 -> 32251761
A34: 2028 | B34: ='Initial Investment & Cashflows'!B295 -> 65585695
A39: Discount Rate | B39: PV of Cash Flows | C39: NPV
A40: 0.0884 | B40: =NPV(A40,B32:B34) -> 96200849 | C40: =B31+B40 -> 6200848.8 | D40: wacc
A41: 0.1 | B41: =NPV(A41,B32:B34) -> 93846351 | C41: =B31+B41 -> 3846350.5
A42: 0.11 | B42: =NPV(A42,B32:B34) -> 91887037 | C42: =B31+B42 -> 1887037
A43: 0.12 | B43: =NPV(A43,B32:B34) -> 89990070 | C43: =B31+B43 -> -9929.6003 | D43: Given rate
