Workbook

Sheet Business Line By Segm
A1: Company Fundamentals - Segments
A2: Company Name | B2: Lululemon Athletica Inc (LULU.O)
A3: Country of Exchange | B3: United States of America
A4: Country of Headquarters | B4: Canada
A5: TRBC Industry Group | B5: Textiles & Apparel
A6: CF Template | B6: IND
A7: Consolidation Basis | B7: Consolidated
A8: Scaling | B8: Millions
A9: Period | B9: Annual
A10: Export Date | B10: 45922.395
A11: Statement Data | C11: 2025 | D11: 2024 | E11: 2023 | F11: 2022 | G11: 2021 | H11: 2020 | I11: 2019
A12: Period End Date | C12: 45690 | D12: 45319 | E12: 44955 | F12: 44591 | G12: 44227 | H12: 43863 | I12: 43499
A13: Statement Date | C13: 45690 | D13: 45319 | E13: 45319 | F13: 45319 | G13: 44227 | H13: 43863 | I13: 43499
A14: Standardized Currency | C14: USD | D14: USD | E14: USD | F14: USD | G14: USD | H14: USD | I14: USD
A15: Template Type | C15: Industrial | D15: Industrial | E15: Industrial | F15: Industrial | G15: Industrial | H15: Industrial | I15: Industrial
A17: Segments - Business Line By Segment (Currency: Standardized)
A18: Field Name | B18: TRBC | C18: 02-02-2025 | D18: 28-01-2024 | E18: 29-01-2023 | F18: 30-01-2022 | G18: 31-01-2021 | H18: 02-02-2020 | I18: 03-02-2019
A19: Company-operated stores | B19: 458110
A20: Depreciation & Amortization | G20: 100.78 | H20: 97.9 | I20: 76.3
A21: External Revenue | G21: 1658.81 | H21: 2501.07 | I21: 2126.36
A22: Fixed Assets - Purchased - Cash Flow | G22: 134.2 | H22: 171.5 | I22: 129.16
A23: Operating Income/Loss | G23: 212.59 | H23: 689.34 | I23: 575.54
A24: Direct To Consumers | B24: 315990, 315250
A25: Depreciation & Amortization | G25: 14.85 | H25: 12.47 | I25: 10.02
A26: External Revenue | G26: 2284.07 | H26: 1137.82 | I26: 858.86
A27: Fixed Assets - Purchased - Cash Flow | G27: 37.24 | H27: 15.81 | I27: 6.42
A28: Operating Income/Loss | G28: 1029.1 | H28: 482.37 | I28: 354.11
A29: Corporate & Other
A30: Amortization of Intangibles excluding Goodwill | C30: 2.74
A31: Depreciation & Amortization | C31: 177.52 | D31: 159.58 | E31: 117.34 | F31: 73.89 | G31: 69.86 | H31: 51.57 | I31: 36.16
A32: Fixed Assets - Purchased - Cash Flow | G32: 57.78 | H32: 95.74 | I32: 90.23
A33: Operating Income/Loss | C33: -1334.66 | D33: -1343.66 | E33: -1477.4 | F33: -768.65 | G33: -432.21 | H33: -355.16 | I33: -286.36
A34: Americas | B34: 315990, 315210, 458110
A35: Depreciation & Amortization | C35: 204.92 | D35: 170.42 | E35: 137.26 | F35: 121.28
A36: External Revenue | C36: 7928.16 | D36: 7631.65 | E36: 6817.45 | F36: 5299.91
A37: Operating Income/Loss | C37: 3015.56 | D37: 2937.18 | E37: 2503.74 | F37: 1867.02
A38: China Mainland | B38: 315990, 315210, 458110
A39: Depreciation & Amortization | C39: 33.21 | D39: 25.75 | E39: 17.84 | F39: 12.21
A40: External Revenue | C40: 1361.34 | D40: 963.76 | E40: 576.5 | F40: 434.26
A41: Operating Income/Loss | C41: 509.86 | D41: 337.32 | E41: 196.87 | F41: 167.32
A42: Rest of World | B42: 315990, 315210, 458110
A43: Depreciation & Amortization | C43: 30.87 | D43: 23.64 | E43: 19.35 | F43: 16.83
A44: External Revenue | C44: 1298.63 | D44: 1023.87 | E44: 716.56 | F44: 522.45
A45: Operating Income/Loss | C45: 314.95 | D45: 201.83 | E45: 103.2 | F45: 67.67
A46: Other
A47: External Revenue | G47: 459 | H47: 340.41 | I47: 303.1
A48: Operating Income/Loss | G48: 10.5 | H48: 72.56 | I48: 62.56
A49: Total
A50: Amortization of Intangibles excluding Goodwill | C50: 2.74
A51: Depreciation & Amortization | C51: 446.52 | D51: 379.38 | E51: 291.79 | F51: 224.21 | G51: 185.48 | H51: 161.93 | I51: 122.48
A52: External Revenue | C52: 10588.13 | D52: 9619.28 | E52: 8110.52 | F52: 6256.62 | G52: 4401.88 | H52: 3979.3 | I52: 3288.32
A53: Fixed Assets - Purchased - Cash Flow | G53: 229.23 | H53: 283.05 | I53: 225.81
A54: Operating Income/Loss | C54: 2505.7 | D54: 2132.68 | E54: 1328.41 | F54: 1333.36 | G54: 819.99 | H54: 889.11 | I54: 705.84

Sheet Business Line By Stat
A1: Company Fundamentals - Segments
A2: Company Name | B2: Lululemon Athletica Inc (LULU.O)
A3: Country of Exchange | B3: United States of America
A4: Country of Headquarters | B4: Canada
A5: TRBC Industry Group | B5: Textiles & Apparel
A6: CF Template | B6: IND
A7: Consolidation Basis | B7: Consolidated
A8: Scaling | B8: Millions
A9: Period | B9: Annual
A10: Export Date | B10: 45922.395
A11: Statement Data | C11: 2025 | D11: 2024 | E11: 2023 | F11: 2022 | G11: 2021 | H11: 2020 | I11: 2019
A12: Period End Date | C12: 45690 | D12: 45319 | E12: 44955 | F12: 44591 | G12: 44227 | H12: 43863 | I12: 43499
A13: Statement Date | C13: 45690 | D13: 45319 | E13: 44955 | F13: 44591 | G13: 44227 | H13: 43863 | I13: 43499
A14: Standardized Currency | C14: USD | D14: USD | E14: USD | F14: USD | G14: USD | H14: USD | I14: USD
A15: Template Type | C15: Industrial - Gross Profit | D15: Industrial - Gross Profit | E15: Industrial - Gross Profit | F15: Industrial - Gross Profit | G15: Industrial - Gross Profit | H15: Industrial - Gross Profit | I15: Industrial - Gross Profit
A17: Segments - Business Line By Statement Item (Currency: Standardized)
A18: Field Name | B18: TRBC | C18: 02-02-2025 | D18: 28-01-2024 | E18: 29-01-2023 | F18: 30-01-2022 | G18: 31-01-2021 | H18: 02-02-2020 | I18: 03-02-2019
A19: Fixed Assets - Purchased - Cash Flow | G19: 229.23 | H19: 283.05 | I19: 225.81
A20: Company-operated stores | B20: 458110 | G20: 134.2 | H20: 171.5 | I20: 129.16
A21: Corporate & Other | G21: 57.78 | H21: 95.74 | I21: 90.23
A22: Direct To Consumers | B22: 315990, 315250 | G22: 37.24 | H22: 15.81 | I22: 6.42
A23: Operating Income/Loss | C23: 2505.7 | D23: 2132.68 | E23: 1328.41 | F23: 1333.36 | G23: 819.99 | H23: 889.11 | I23: 705.84
A24: Americas | B24: 315990, 315210, 458110 | C24: 3015.56 | D24: 2937.18 | E24: 2503.74 | F24: 1867.02
A25: China Mainland | B25: 315990, 315210, 458110 | C25: 509.86 | D25: 337.32 | E25: 196.87 | F25: 167.32
A26: Company-operated stores | B26: 458110 | G26: 212.59 | H26: 689.34 | I26: 575.54
A27: Corporate & Other | C27: -1334.66 | D27: -1343.66 | E27: -1477.4 | F27: -768.65 | G27: -432.21 | H27: -355.16 | I27: -286.36
A28: Direct To Consumers | B28: 315990, 315250 | G28: 1029.1 | H28: 482.37 | I28: 354.11
A29: Other | G29: 10.5 | H29: 72.56 | I29: 62.56
A30: Rest of World | B30: 315990, 315210, 458110 | C30: 314.95 | D30: 201.83 | E30: 103.2 | F30: 67.67
A31: External Revenue | C31: 10588.13 | D31: 9619.28 | E31: 8110.52 | F31: 6256.62 | G31: 4401.88 | H31: 3979.3 | I31: 3288.32
A32: Americas | B32: 315990, 315210, 458110 | C32: 7928.16 | D32: 7631.65 | E32: 6817.45 | F32: 5299.91
A33: China Mainland | B33: 315990, 315210, 458110 | C33: 1361.34 | D33: 963.76 | E33: 576.5 | F33: 434.26
A34: Company-operated stores | B34: 458110 | G34: 1658.81 | H34: 2501.07 | I34: 2126.36
A35: Direct To Consumers | B35: 315990, 315250 | G35: 2284.07 | H35: 1137.82 | I35: 858.86
A36: Other | G36: 459 | H36: 340.41 | I36: 303.1
A37: Rest of World | B37: 315990, 315210, 458110 | C37: 1298.63 | D37: 1023.87 | E37: 716.56 | F37: 522.45
A38: Depreciation & Amortization | C38: 446.52 | D38: 379.38 | E38: 291.79 | F38: 224.21 | G38: 185.48 | H38: 161.93 | I38: 122.48
A39: Americas | B39: 315990, 315210, 458110 | C39: 204.92 | D39: 170.42 | E39: 137.26 | F39: 121.28
A40: China Mainland | B40: 315990, 315210, 458110 | C40: 33.21 | D40: 25.75 | E40: 17.84 | F40: 12.21
A41: Company-operated stores | B41: 458110 | G41: 100.78 | H41: 97.9 | I41: 76.3
A42: Corporate & Other | C42: 177.52 | D42: 159.58 | E42: 117.34 | F42: 73.89 | G42: 69.86 | H42: 51.57 | I42: 36.16
A43: Direct To Consumers | B43: 315990, 315250 | G43: 14.85 | H43: 12.47 | I43: 10.02
A44: Rest of World | B44: 315990, 315210, 458110 | C44: 30.87 | D44: 23.64 | E44: 19.35 | F44: 16.83
A45: Amortization of Intangibles excluding Goodwill | C45: 2.74
A46: Corporate & Other | C46: 2.74

Sheet Geographic Line By Se
A1: Company Fundamentals - Segments
A2: Company Name | B2: Lululemon Athletica Inc (LULU.O)
A3: Country of Exchange | B3: United States of America
A4: Country of Headquarters | B4: Canada
A5: TRBC Industry Group | B5: Textiles & Apparel
A6: CF Template | B6: IND
A7: Consolidation Basis | B7: Consolidated
A8: Scaling | B8: Millions
A9: Period | B9: Annual
A10: Export Date | B10: 45922.395
A11: Statement Data | B11: 2025 | C11: 2024 | D11: 2023 | E11: 2022 | F11: 2021 | G11: 2020 | H11: 2019
A12: Period End Date | B12: 45690 | C12: 45319 | D12: 44955 | E12: 44591 | F12: 44227 | G12: 43863 | H12: 43499
A13: Statement Date | B13: 45690 | C13: 45319 | D13: 44955 | E13: 44591 | F13: 44227 | G13: 43863 | H13: 43499
A14: Standardized Currency | B14: USD | C14: USD | D14: USD | E14: USD | F14: USD | G14: USD | H14: USD
A15: Template Type | B15: Industrial | C15: Industrial | D15: Industrial | E15: Industrial | F15: Industrial | G15: Industrial | H15: Industrial
A17: Segments - Geographic Line By Segment (Currency: Standardized)
A18: Field Name | B18: 02-02-2025 | C18: 28-01-2024 | D18: 29-01-2023 | E18: 30-01-2022 | F18: 31-01-2021 | G18: 02-02-2020 | H18: 03-02-2019
A19: United States
A20: Employees - Full-Time/Full-Time Equivalents - Period End | G20: 11000 | H20: 9200
A21: External Revenue | B21: 6483.18 | C21: 6346.39 | D21: 5654.34 | E21: 4345.69 | F21: 3105.13 | G21: 2854.36 | H21: 2363.37
A22: Long-lived Assets | B22: 1788.55 | C22: 1597.32
A23: Net Income before Tax | B23: 479.96 | C23: 458.04 | D23: -98.76 | E23: 204.35 | F23: 122.57 | G23: 180.04 | H23: 132.56
A24: Property, Plant & Equipment - Net - Total | D24: 671.21 | E24: 418.32 | F24: 267.33 | G24: 259.49 | H24: 217.87
A25: Canada
A26: Employees - Full-Time/Full-Time Equivalents - Period End | G26: 5200 | H26: 4200
A27: External Revenue | B27: 1411.67 | C27: 1285.26 | D27: 1163.11 | E27: 954.22 | F27: 672.61 | G27: 649.11 | H27: 565.11
A28: Long-lived Assets | B28: 675.05 | C28: 671.62
A29: Property, Plant & Equipment - Net - Total | D29: 431.35 | E29: 392.19 | F29: 394.86 | G29: 346.31 | H29: 303.06
A30: Outside of the North America
A31: Employees - Full-Time/Full-Time Equivalents - Period End | G31: 2800 | H31: 2200
A32: External Revenue | C32: 853.34 | D32: 611.43 | E32: 956.71 | F32: 624.14 | G32: 475.82 | H32: 359.84
A33: Long-lived Assets | C33: 257.91
A34: Property, Plant & Equipment - Net - Total | D34: 167.05 | E34: 117.2 | F34: 83.5 | G34: 65.9 | H34: 46.3
A35: People's Republic of China
A36: External Revenue | B36: 1541.43 | C36: 1134.29 | D36: 681.63
A37: Long-lived Assets | B37: 326.62 | C37: 284.58
A38: Other geographic areas
A39: External Revenue | B39: 1118.54
A40: Long-lived Assets | B40: 406.65
A41: Mexico
A42: External Revenue | B42: 33.3
A43: Foreign
A44: Net Income before Tax | B44: 2096.12 | C44: 1717.69 | D44: 1431.34 | E44: 1129.52 | F44: 696.78 | G44: 717.35 | H44: 582.69
A45: Total
A46: Employees - Full-Time/Full-Time Equivalents - Period End | G46: 19000 | H46: 15600
A47: External Revenue | B47: 10588.13 | C47: 9619.28 | D47: 8110.52 | E47: 6256.62 | F47: 4401.88 | G47: 3979.3 | H47: 3288.32
A48: International Assets | B48: 2521.82 | C48: 2139.8
A49: International Sales | B49: 9176.45 | C49: 8334.02 | D49: 6947.41 | E49: 5302.4 | F49: 3729.27 | G49: 3330.18 | H49: 2723.21
A50: Long-lived Assets | B50: 3196.87 | C50: 2811.42
A51: Net Income before Tax | B51: 2576.08 | C51: 2175.74 | D51: 1332.57 | E51: 1333.87 | F51: 819.35 | G51: 897.39 | H51: 715.25
A52: Property, Plant & Equipment - Net - Total | D52: 1269.61 | E52: 927.71 | F52: 745.69 | G52: 671.69 | H52: 567.24

Sheet Geographic Line By St
A1: Company Fundamentals - Segments
A2: Company Name | B2: Lululemon Athletica Inc (LULU.O)
A3: Country of Exchange | B3: United States of America
A4: Country of Headquarters | B4: Canada
A5: TRBC Industry Group | B5: Textiles & Apparel
A6: CF Template | B6: IND
A7: Consolidation Basis | B7: Consolidated
A8: Scaling | B8: Millions
A9: Period | B9: Annual
A10: Export Date | B10: 45922.395
A11: Statement Data | B11: 2025 | C11: 2024 | D11: 2023 | E11: 2022 | F11: 2021 | G11: 2020 | H11: 2019
A12: Period End Date | B12: 45690 | C12: 45319 | D12: 44955 | E12: 44591 | F12: 44227 | G12: 43863 | H12: 43499
A13: Statement Date | B13: 45690 | C13: 45319 | D13: 44955 | E13: 44591 | F13: 44227 | G13: 43863 | H13: 43499
A14: Standardized Currency | B14: USD | C14: USD | D14: USD | E14: USD | F14: USD | G14: USD | H14: USD
A15: Template Type | B15: Industrial - Gross Profit | C15: Industrial - Gross Profit | D15: Industrial - Gross Profit | E15: Industrial - Gross Profit | F15: Industrial - Gross Profit | G15: Industrial - Gross Profit | H15: Industrial - Gross Profit
A17: Segments - Geographic Line By Statement Item (Currency: Standardized)
A18: Field Name | B18: 02-02-2025 | C18: 28-01-2024 | D18: 29-01-2023 | E18: 30-01-2022 | F18: 31-01-2021 | G18: 02-02-2020 | H18: 03-02-2019
A19: Employees - Full-Time/Full-Time Equivalents - Period End | G19: 19000 | H19: 15600
A20: Canada | G20: 5200 | H20: 4200
A21: Outside of the North America | G21: 2800 | H21: 2200
A22: United States | G22: 11000 | H22: 9200
A23: External Revenue | B23: 10588.13 | C23: 9619.28 | D23: 8110.52 | E23: 6256.62 | F23: 4401.88 | G23: 3979.3 | H23: 3288.32
A24: Canada | B24: 1411.67 | C24: 1285.26 | D24: 1163.11 | E24: 954.22 | F24: 672.61 | G24: 649.11 | H24: 565.11
A25: Mexico | B25: 33.3
A26: Other geographic areas | B26: 1118.54
A27: Outside of the North America | C27: 853.34 | D27: 611.43 | E27: 956.71 | F27: 624.14 | G27: 475.82 | H27: 359.84
A28: People's Republic of China | B28: 1541.43 | C28: 1134.29 | D28: 681.63
A29: United States | B29: 6483.18 | C29: 6346.39 | D29: 5654.34 | E29: 4345.69 | F29: 3105.13 | G29: 2854.36 | H29: 2363.37
A30: International Assets | B30: 2521.82 | C30: 2139.8
A31: International Sales | B31: 9176.45 | C31: 8334.02 | D31: 6947.41 | E31: 5302.4 | F31: 3729.27 | G31: 3330.18 | H31: 2723.21
A32: Property, Plant & Equipment - Net - Total | D32: 1269.61 | E32: 927.71 | F32: 745.69 | G32: 671.69 | H32: 567.24
A33: Canada | D33: 431.35 | E33: 392.19 | F33: 394.86 | G33: 346.31 | H33: 303.06
A34: Outside of the North America | D34: 167.05 | E34: 117.2 | F34: 83.5 | G34: 65.9 | H34: 46.3
A35: United States | D35: 671.21 | E35: 418.32 | F35: 267.33 | G35: 259.49 | H35: 217.87
A36: Net Income before Tax | B36: 2576.08 | C36: 2175.74 | D36: 1332.57 | E36: 1333.87 | F36: 819.35 | G36: 897.39 | H36: 715.25
A37: Foreign | B37: 2096.12 | C37: 1717.69 | D37: 1431.34 | E37: 1129.52 | F37: 696.78 | G37: 717.35 | H37: 582.69
A38: United States | B38: 479.96 | C38: 458.04 | D38: -98.76 | E38: 204.35 | F38: 122.57 | G38: 180.04 | H38: 132.56
A39: Long-lived Assets | B39: 3196.87 | C39: 2811.42
A40: Canada | B40: 675.05 | C40: 671.62
A41: Other geographic areas | B41: 406.65
A42: Outside of the North America | C42: 257.91
A43: People's Republic of China | B43: 326.62 | C43: 284.58
A44: United States | B44: 1788.55 | C44: 1597.32

Sheet Product Line By Segme
A1: Company Fundamentals - Segments
A2: Company Name | B2: Lululemon Athletica Inc (LULU.O)
A3: Country of Exchange | B3: United States of America
A4: Country of Headquarters | B4: Canada
A5: TRBC Industry Group | B5: Textiles & Apparel
A6: CF Template | B6: IND
A7: Consolidation Basis | B7: Consolidated
A8: Scaling | B8: Millions
A9: Period | B9: Annual
A10: Export Date | B10: 45922.395
A11: Statement Data | B11: 2025 | C11: 2024 | D11: 2023 | E11: 2022 | F11: 2021 | G11: 2020
A12: Period End Date | B12: 45690 | C12: 45319 | D12: 44955 | E12: 44591 | F12: 44227 | G12: 43863
A13: Statement Date | B13: 45690 | C13: 45319 | D13: 44955 | E13: 44591 | F13: 44227 | G13: 43863
A14: Standardized Currency | B14: USD | C14: USD | D14: USD | E14: USD | F14: USD | G14: USD
A15: Template Type | B15: Industrial | C15: Industrial | D15: Industrial | E15: Industrial | F15: Industrial | G15: Industrial
A17: Segments - Product Line By Segment (Currency: Standardized)
A18: Field Name | B18: 02-02-2025 | C18: 28-01-2024 | D18: 29-01-2023 | E18: 30-01-2022 | F18: 31-01-2021 | G18: 02-02-2020
A19: Womens Product-Mens Product
A20: External Revenue | B20: 2558.38 | C20: 2252.75 | D20: 1956.6 | E20: 1535.85 | F20: 953.18 | G20: 933.77
A21: Mens Product-Womens Product
A22: External Revenue | B22: 6692.63 | C22: 6147.37 | D22: 5259.8 | E22: 4171.76 | F22: 3049.91 | G22: 2791
A23: Other Categories
A24: External Revenue | B24: 1337.12 | C24: 1219.15 | D24: 894.11 | E24: 549.01 | F24: 398.79 | G24: 254.53
A25: Total
A26: External Revenue | B26: 10588.13 | C26: 9619.28 | D26: 8110.52 | E26: 6256.62 | F26: 4401.88 | G26: 3979.3

Sheet Product Line By State
A1: Company Fundamentals - Segments
A2: Company Name | B2: Lululemon Athletica Inc (LULU.O)
A3: Country of Exchange | B3: United States of America
A4: Country of Headquarters | B4: Canada
A5: TRBC Industry Group | B5: Textiles & Apparel
A6: CF Template | B6: IND
A7: Consolidation Basis | B7: Consolidated
A8: Scaling | B8: Millions
A9: Period | B9: Annual
A10: Export Date | B10: 45922.395
A11: Statement Data | B11: 2025 | C11: 2024 | D11: 2023 | E11: 2022 | F11: 2021 | G11: 2020
A12: Period End Date | B12: 45690 | C12: 45319 | D12: 44955 | E12: 44591 | F12: 44227 | G12: 43863
A13: Statement Date | B13: 45690 | C13: 45319 | D13: 44955 | E13: 44591 | F13: 44227 | G13: 43863
A14: Standardized Currency | B14: USD | C14: USD | D14: USD | E14: USD | F14: USD | G14: USD
A15: Template Type | B15: Industrial | C15: Industrial | D15: Industrial | E15: Industrial | F15: Industrial | G15: Industrial
A17: Segments - Product Line By Statement Item (Currency: Standardized)
A18: Field Name | B18: 02-02-2025 | C18: 28-01-2024 | D18: 29-01-2023 | E18: 30-01-2022 | F18: 31-01-2021 | G18: 02-02-2020
A19: External Revenue | B19: 10588.13 | C19: 9619.28 | D19: 8110.52 | E19: 6256.62 | F19: 4401.88 | G19: 3979.3
A20: Mens Product-Womens Product | B20: 6692.63 | C20: 6147.37 | D20: 5259.8 | E20: 4171.76 | F20: 3049.91 | G20: 2791
A21: Other Categories | B21: 1337.12 | C21: 1219.15 | D21: 894.11 | E21: 549.01 | F21: 398.79 | G21: 254.53
A22: Womens Product-Mens Product | B22: 2558.38 | C22: 2252.75 | D22: 1956.6 | E22: 1535.85 | F22: 953.18 | G22: 933.77

Sheet Income Statement
A1: Company Fundamentals - Income Statement
A2: Company Name | B2: Lululemon Athletica Inc (LULU.O)
A3: Country of Exchange | B3: United States of America
A4: Country of Headquarters | B4: Canada
A5: TRBC Industry Group | B5: Textiles & Apparel
A6: CF Template | B6: IND
A7: Consolidation Basis | B7: Consolidated
A8: Scaling | B8: Millions
A9: Period | B9: Annual
A10: Export Date | B10: 45922.395
A11: Statement Data | B11: 2025 | C11: 2024 | D11: 2023 | E11: 2022 | F11: 2021 | G11: 2020 | H11: 2019
A12: Period End Date | B12: 45690 | C12: 45319 | D12: 44955 | E12: 44591 | F12: 44227 | G12: 43863 | H12: 43499
A13: Statement Date | B13: 45690 | C13: 45319 | D13: 44955 | E13: 44591 | F13: 44227 | G13: 43863 | H13: 43499
A14: Standardized Currency | B14: USD | C14: USD | D14: USD | E14: USD | F14: USD | G14: USD | H14: USD
A15: Template Type | B15: Industrial - Gross Profit | C15: Industrial - Gross Profit | D15: Industrial - Gross Profit | E15: Industrial - Gross Profit | F15: Industrial - Gross Profit | G15: Industrial - Gross Profit | H15: Industrial - Gross Profit
A17: Income Statement - Standardized (Currency: Standardized)
A18: Field Name | B18: 02-02-2025 | C18: 28-01-2024 | D18: 29-01-2023 | E18: 30-01-2022 | F18: 31-01-2021 | G18: 02-02-2020 | H18: 03-02-2019
A19: Revenues
A20: Revenue from Goods & Services | B20: 10588.13 | C20: 9619.28 | D20: 8110.52 | E20: 6256.62 | F20: 4401.88 | G20: 3979.3 | H20: 3288.32
A21: Sales of Goods & Services - Net - Unclassified | B21: 10588.13 | C21: 9619.28 | D21: 8110.52 | E21: 6256.62 | F21: 4401.88 | G21: 3979.3 | H21: 3288.32
A22: Revenue from Business Activities - Total | B22: 10588.13 | C22: 9619.28 | D22: 8110.52 | E22: 6256.62 | F22: 4401.88 | G22: 3979.3 | H22: 3288.32
A23: Operating Expenses
A24: Cost of Operating Revenue | B24: 4320.05 | C24: 4014.88 | D24: 3626.93 | E24: 2656.83 | F24: 1943.05 | G24: 1755.91 | H24: 1472.03
A25: Cost of Revenues - Total | B25: 4320.05 | C25: 4014.88 | D25: 3626.93 | E25: 2656.83 | F25: 1943.05 | G25: 1755.91 | H25: 1472.03
A26: Cost of Revenues - Unclassified | B26: 4317.31 | C26: 4009.87 | D26: 3618.18 | E26: 2648.05 | F26: 1937.89
A27: Amortization in Cost of Revenues | B27: 2.74 | C27: 5.01 | D27: 8.75 | E27: 8.78 | F27: 5.16
A28: Gross Profit - Industrials/Property - Total | B28: 6268.08 | C28: 5604.4 | D28: 4483.59 | E28: 3599.78 | F28: 2458.83 | G28: 2223.39 | H28: 1816.29
A29: Selling, General & Administrative Expenses - Total | B29: 3758.88 | C29: 3397.22 | D29: 2757.45 | E29: 2225.03 | F29: 1609 | G29: 1332.77 | H29: 1111.84
A30: Selling, General & Administrative Expenses - Unclassified | B30: 3217.38
A31: Selling, General & Administrative Expenses - Other - Total | B31: 541.5
A32: Advertising Expense | B32: 541.5
A33: Operating Expenses - Total | B33: 8078.93 | C33: 7412.1 | D33: 6384.38 | E33: 4881.87 | F33: 3552.05 | G33: 3088.68 | H33: 2583.88
A34: Operating Profit
A35: Operating Profit before Non-Recurring Income/Expense | B35: 2509.2 | C35: 2207.18 | D35: 1726.14 | E35: 1374.75 | F35: 849.83 | G35: 890.62 | H35: 704.44
A36: Non-Operating Expenses
A37: Financing Income/(Expense) - Net - Total
A38: Interest Expense - Net of (Interest Income) | D38: -67.9 | E38: -35.8 | F38: -23.5 | G38: -0.02 | H38: -0.01
A39: Interest Expense - Net of Capitalized Interest | D39: -67.9 | E39: -35.8 | F39: -23.5 | G39: -0.02 | H39: -0.01
A40: Interest Capitalized | D40: 67.9 | E40: 35.8 | F40: 23.5 | G40: 0.02 | H40: 0.01
A41: Non-Interest Financial Income/(Expense) - Total | D41: -67.9 | E41: -35.8 | F41: -23.5 | G41: -0.02 | H41: -0.01
A42: Non-Interest Financial Income/(Expense) - Other - Net | D42: -67.9 | E42: -35.8 | F42: -23.5 | G42: -0.02 | H42: -0.01
A43: Sale of Tangible & Intangible Fixed Assets - Gain/(Loss) | D43: 10.18
A44: Other Non-Operating Income/(Expense) - Total | B44: 70.38 | C44: 43.06 | D44: 4.16 | E44: 0.51 | F44: -0.64 | G44: 8.28 | H44: 9.41
A45: Normalized Pre-tax Profit | B45: 2579.58 | C45: 2250.24 | D45: 1740.48 | E45: 1375.26 | F45: 849.19 | G45: 898.9 | H45: 713.86
A46: Non-Recurring Income/Expense
A47: Non-Recurring Income/(Expense) - Total | B47: -3.5 | C47: -74.5 | D47: -407.91 | E47: -41.39 | F47: -29.84 | G47: -1.51 | H47: 1.39
A48: Impairment - Tangible & Intangible Fixed Assets | C48: 44.19 | D48: 407.91
A49: Impairment - Fixed Assets | C49: 11.16 | D49: 407.91
A50: Impairment - Intangibles excluding Goodwill | C50: 33.03
A51: Restructuring Charges | C51: 30.32
A52: Unrealized Adjustments on Derivatives for Hedging | G52: -1.51 | H52: 1.39
A53: Sale & Acquisition of Group Companies - Gain/(Loss) | B53: -3.5 | E53: -41.39 | F53: -29.84
A54: Pre-Tax Income
A55: Income before Taxes | B55: 2576.08 | C55: 2175.74 | D55: 1332.57 | E55: 1333.87 | F55: 819.35 | G55: 897.39 | H55: 715.25
A56: Taxes
A57: Income Taxes | B57: 761.46 | C57: 625.54 | D57: 477.77 | E57: 358.55 | F57: 230.44 | G57: 251.8 | H57: 223.99
A58: Income Taxes for the Year - Current | B58: 703.08 | C58: 652.29 | D58: 468.37 | E58: 365.41 | F58: 196.31 | G58: 227.4 | H58: 205.03
A59: Income Taxes - Domestic - Current | B59: 118.83 | C59: 183.2 | D59: 68.12 | E59: 43.31 | F59: 10.51 | G59: 57.25 | H59: 81.9
A60: Income Taxes - Foreign - Current | B60: 584.25 | C60: 469.09 | D60: 400.25 | E60: 322.11 | F60: 185.8 | G60: 170.16 | H60: 123.13
A61: Income Taxes - Deferred | B61: 58.38 | C61: -26.75 | D61: 9.4 | E61: -6.87 | F61: 34.13 | G61: 24.39 | H61: 18.95
A62: Income Taxes - Domestic - Deferred | B62: 75.43 | C62: -17.84 | D62: 11.3 | E62: 6.9 | F62: 25.68 | G62: -5.83 | H62: -21.63
A63: Income Taxes - Foreign - Deferred | B63: -17.05 | C63: -8.91 | D63: -1.89 | E63: -13.77 | F63: 8.45 | G63: 30.23 | H63: 40.59
A64: Net Income After Tax
A65: Net Income after Tax | B65: 1814.62 | C65: 1550.19 | D65: 854.8 | E65: 975.32 | F65: 588.91 | G65: 645.6 | H65: 491.27
A66: After Tax Income/Expense
A67: Income before Discontinued Operations & Extraordinary Items | B67: 1814.62 | C67: 1550.19 | D67: 854.8 | E67: 975.32 | F67: 588.91 | G67: 645.6 | H67: 491.27
A68: Extraordinary Activities - after Tax - Gain/(Loss) | H68: -7.46
A69: Extraordinary Items | H69: -7.46
A70: Net Income before Minority Interest | B70: 1814.62 | C70: 1550.19 | D70: 854.8 | E70: 975.32 | F70: 588.91 | G70: 645.6 | H70: 483.8
A71: Net Income after Minority Interest | B71: 1814.62 | C71: 1550.19 | D71: 854.8 | E71: 975.32 | F71: 588.91 | G71: 645.6 | H71: 483.8
A72: Net Income
A73: Income Available to Common Shares | B73: 1814.62 | C73: 1550.19 | D73: 854.8 | E73: 975.32 | F73: 588.91 | G73: 645.6 | H73: 483.8
A74: Other Comprehensive Income
A75: Other Comprehensive Income - Starting Line | B75: 1814.62 | C75: 1550.19 | D75: 854.8 | E75: 975.32 | F75: 588.91 | G75: 645.6 | H75: 483.8
A76: Other Comprehensive Income - Foreign Currency | B76: -253.21 | C76: -23.08 | D76: -65.57 | E76: -28.49 | F76: 47.43 | G76: -7.77 | H76: -73.89
A77: Other Comprehensive Income - Unrealized Investment Gain/(Loss) | B77: 93.02 | C77: 11.41 | D77: 8.9 | E77: 9.73
A78: Other Comprehensive Income - Net of Tax - Total | B78: -160.18 | C78: -11.67 | D78: -56.67 | E78: -18.76 | F78: 47.43 | G78: -7.77 | H78: -73.89
A79: Comprehensive Income before Minority Interest - Total | B79: 1654.43 | C79: 1538.52 | D79: 798.13 | E79: 956.56 | F79: 636.34 | G79: 637.82 | H79: 409.92
A80: Comprehensive Income - Attributable to Parent Company Equity Holders - Total | B80: 1654.43 | C80: 1538.52 | D80: 798.13 | E80: 956.56 | F80: 636.34 | G80: 637.82 | H80: 409.92
A81: Share/Per Share - Basic
A82: Net Income - Basic - including Extraordinary Items Applicable to Common - Total | B82: 1814.62 | C82: 1550.19 | D82: 854.8 | E82: 975.32 | F82: 588.91 | G82: 645.6 | H82: 483.8
A83: Income available to Common excluding Extraordinary Items | B83: 1814.62 | C83: 1550.19 | D83: 854.8 | E83: 975.32 | F83: 588.91 | G83: 645.6 | H83: 491.27
A84: Shares used to calculate Basic EPS - Total | B84: 123.74 | C84: 126.73 | D84: 127.67 | E84: 129.77 | F84: 130.29 | G84: 130.39 | H84: 133.41
A85: EPS - Basic - including Extraordinary Items Applicable to Common - Total | B85: 14.67 | C85: 12.23 | D85: 6.7 | E85: 7.52 | F85: 4.52 | G85: 4.95 | H85: 3.63
A86: EPS - Basic - excluding Extraordinary Items Applicable to Common - Total | B86: 14.67 | C86: 12.23 | D86: 6.7 | E86: 7.52 | F86: 4.52 | G86: 4.95 | H86: 3.68
A87: EPS - Basic - excluding Extraordinary Items - Normalized - Total | B87: 14.69 | C87: 12.82 | D87: 9.89 | E87: 7.83 | F87: 4.75 | G87: 4.96 | H87: 3.67
A88: EPS - Basic from Discontinued Operations & Extraordinary Items | H88: -0.06
A89: Share/Per Share - Diluted
A90: Net Income - Diluted - including Extraordinary Items Applicable to Common - Total | B90: 1814.62 | C90: 1550.19 | D90: 854.8 | E90: 975.32 | F90: 588.91 | G90: 645.6 | H90: 483.8
A91: Diluted Income available to Common excluding Extraordinary Items | B91: 1814.62 | C91: 1550.19 | D91: 854.8 | E91: 975.32 | F91: 588.91 | G91: 645.6 | H91: 491.27
A92: Shares used to calculate Diluted EPS - Total | B92: 123.94 | C92: 127.06 | D92: 128.02 | E92: 130.29 | F92: 130.87 | G92: 130.96 | H92: 133.97
A93: EPS - Diluted - including Extraordinary Items Applicable to Common - Total | B93: 14.64 | C93: 12.2 | D93: 6.68 | E93: 7.49 | F93: 4.5 | G93: 4.93 | H93: 3.61
A94: EPS - Diluted - excluding Extraordinary Items Applicable to Common - Total | B94: 14.64 | C94: 12.2 | D94: 6.68 | E94: 7.49 | F94: 4.5 | G94: 4.93 | H94: 3.67
A95: EPS - Diluted - excluding Extraordinary Items - Normalized - Total | B95: 14.67 | C95: 12.79 | D95: 9.86 | E95: 7.8 | F95: 4.73 | G95: 4.94 | H95: 3.66
A96: EPS - Diluted from Discontinued Operations & Extraordinary Items | H96: -0.06
A97: Share/Per Share - Dividends
A98: DPS - Common - Gross - Issue - By Announcement Date
A99: DPS - Common - Gross - Issue - By Announcement Date
A100: DPS - Common - Gross - Issue - By Announcement Date
A101: DPS - Common - Net - Issue - By Announcement Date
...

Sheet Balance Sheet
A1: Company Fundamentals - Balance Sheet
A2: Company Name | B2: Lululemon Athletica Inc (LULU.O)
A3: Country of Exchange | B3: United States of America
A4: Country of Headquarters | B4: Canada
A5: TRBC Industry Group | B5: Textiles & Apparel
A6: CF Template | B6: IND
A7: Consolidation Basis | B7: Consolidated
A8: Scaling | B8: Millions
A9: Period | B9: Annual
A10: Export Date | B10: 45922.395
A11: Statement Data | B11: 2025 | C11: 2024 | D11: 2023 | E11: 2022 | F11: 2021 | G11: 2020 | H11: 2019
A12: Period End Date | B12: 45690 | C12: 45319 | D12: 44955 | E12: 44591 | F12: 44227 | G12: 43863 | H12: 43499
A13: Statement Date | B13: 45690 | C13: 45319 | D13: 44955 | E13: 44591 | F13: 44227 | G13: 43863 | H13: 43499
A14: Standardized Currency | B14: USD | C14: USD | D14: USD | E14: USD | F14: USD | G14: USD | H14: USD
A15: Template Type | B15: Industrial - Differentiated | C15: Industrial - Differentiated | D15: Industrial - Differentiated | E15: Industrial - Differentiated | F15: Industrial - Differentiated | G15: Industrial - Differentiated | H15: Industrial - Differentiated
A17: Balance Sheet - Standardized (Currency: Standardized)
A18: Field Name | B18: 02-02-2025 | C18: 28-01-2024 | D18: 29-01-2023 | E18: 30-01-2022 | F18: 31-01-2021 | G18: 02-02-2020 | H18: 03-02-2019
A19: Current Assets
A20: Cash & Short-Term Investments | B20: 1984.34 | C20: 2243.97 | D20: 1154.87 | E20: 1259.87 | F20: 1150.52 | G20: 1093.51 | H20: 881.32
A21: Cash & Cash Equivalents | B21: 1984.34 | C21: 2243.97 | D21: 1154.87 | E21: 1259.87 | F21: 1150.52 | G21: 1093.51 | H21: 881.32
A22: Derivative Financial Instruments - Hedging - Short-Term | B22: 76.85 | C22: 0.65 | D22: 16.71 | E22: 19.08 | F22: 17.36 | G22: 0.15 | H22: 0.52
A23: Loans & Receivables - Net - Short-Term | B23: 120.17 | C23: 124.77 | D23: 132.91 | E23: 77 | F23: 75.71 | G23: 40.22 | H23: 35.79
A24: Trade Accounts & Trade Notes Receivable - Net | B24: 120.17 | C24: 124.77 | D24: 132.91 | E24: 77 | F24: 62.4 | G24: 40.22 | H24: 35.79
A25: Receivables - Other - Total | F25: 13.31
A26: Inventories - Total | B26: 1442.08 | C26: 1323.6 | D26: 1447.37 | E26: 966.48 | F26: 647.23 | G26: 518.51 | H26: 404.84
A27: Inventories - Finished Goods | B27: 1526.06 | C27: 1465.08 | D27: 1571.98 | E27: 1004.53 | F27: 678.2 | G27: 540.58 | H27: 420.93
A28: Inventories - Other - Total | B28: -83.97 | C28: -141.47 | D28: -124.61 | E28: -38.04 | F28: -30.97 | G28: -22.07 | H28: -16.09
A29: Prepaid Expenses - Short-Term | B29: 329.93 | C29: 320.94 | D29: 327.64 | E29: 259.87 | F29: 221.29 | G29: 155.55 | H29: 106.82
A30: Other Current Assets - Total | B30: 26.93 | C30: 46.65 | D30: 79.96 | E30: 32.55 | F30: 12.27
A31: Other Current Assets | B31: 26.93 | C31: 46.65 | D31: 79.96 | E31: 32.55 | F31: 12.27
A32: Total Current Assets | B32: 3980.3 | C32: 4060.58 | D32: 3159.45 | E32: 2614.85 | F32: 2124.38 | G32: 1807.94 | H32: 1429.28
A33: Non-Current Assets
A34: Property, Plant & Equipment - Net - Total | B34: 3196.87 | C34: 2811.42 | D34: 2239.03 | E34: 1731.25 | F34: 1480.52 | G34: 1361.36 | H34: 567.24
A35: Property, Plant & Equipment - excluding Assets Leased Out - Net - Total | B35: 3196.87 | C35: 2811.42 | D35: 2239.03 | E35: 1731.25 | F35: 1480.52 | G35: 1361.36 | H35: 567.24
A36: Property, Plant & Equipment - Gross - Total | B36: 4657.92 | C36: 4028.85 | D36: 3226.33 | E36: 2560.39 | F36: 2171.11 | G36: 1883.03 | H36: 972.48
A37: Property, Plant & Equipment - excluding Assets Leased Out - Gross | B37: 4657.92 | C37: 4028.85 | D37: 3226.33 | E37: 2560.39 | F37: 2171.11 | G37: 1883.03 | H37: 972.48
A38: Land & Buildings - Gross | B38: 1329.36 | C38: 1115.46 | D38: 927.61 | E38: 781.94 | F38: 688.44 | G38: 591.22 | H38: 479.24
A39: Land/Improvements - Gross | B39: 74.46 | C39: 79.5 | D39: 80.69 | E39: 74.3 | F39: 74.26 | G39: 71.83 | H39: 78.64
A40: Buildings - Gross | B40: 27.66 | C40: 29.03 | D40: 28.85 | E40: 30.88 | F40: 30.87 | G40: 30.19 | H40: 38.03
A41: Leasehold Improvements - Gross | B41: 1227.25 | C41: 1006.93 | D41: 818.07 | E41: 676.76 | F41: 583.3 | G41: 489.2 | H41: 362.57
A42: Plant, Machinery & Equipment - Gross | B42: 1476.8 | C42: 1209.16 | D42: 909.06 | E42: 663.21 | F42: 543.55 | G42: 432.17 | H42: 300.23
A43: Computer Software & Equipment - Gross | B43: 1476.8 | C43: 1209.16 | D43: 909.06 | E43: 663.21 | F43: 543.55 | G43: 432.17 | H43: 300.23
A44: Construction in Progress - Gross | B44: 206.4 | C44: 247.94 | D44: 244.9 | E44: 163.42 | F44: 69.85 | G44: 40.93 | H44: 74.27
A45: Right of Use Tangible Assets - Total - Gross | B45: 1416.26 | C45: 1265.61 | D45: 969.42 | E45: 803.54 | F45: 734.84 | G45: 689.66
A46: Right of Use Tangible Assets - Operating Lease - Gross | B46: 1416.26 | C46: 1265.61 | D46: 969.42 | E46: 803.54 | F46: 734.84 | G46: 689.66
A47: Property, Plant & Equipment - Other - Gross | B47: 229.1 | C47: 190.67 | D47: 175.34 | E47: 148.27 | F47: 134.44 | G47: 129.05 | H47: 118.74
A48: Property, Plant & Equipment - Accumulated Depreciation & Impairment - Total | B48: 1461.05 | C48: 1217.43 | D48: 987.3 | E48: 829.13 | F48: 690.59 | G48: 521.68 | H48: 405.24
A49: Property, Plant & Equipment - excluding Assets Leased Out - Accumulated Depreciation & Impairment - Total | B49: 1461.05 | C49: 1217.43 | D49: 987.3 | E49: 829.13 | F49: 690.59 | G49: 521.68 | H49: 405.24
A50: Other Non-Current Assets - Total | B50: 254.93 | C50: 195.86 | D50: 162.45 | E50: 138.19 | F50: 113.36 | G50: 87.64 | H50: 63.95
A51: Deferred Tax - Asset - Long-Term | B51: 17.09 | C51: 9.18 | D51: 6.4 | E51: 6.09 | F51: 6.73 | G51: 31.44 | H51: 26.55
A52: Other Non-Current Assets | B52: 237.84 | C52: 186.68 | D52: 156.04 | E52: 132.1 | F52: 106.63 | G52: 56.2 | H52: 37.4
A53: Intangible Assets - Total - Net | B53: 171.19 | C53: 24.08 | D53: 46.11 | E53: 458.18 | F53: 466.96 | G53: 24.42 | H53: 24.24
A54: Goodwill/Cost in Excess of Assets Purchased - Net | B54: 159.52 | C54: 24.08 | D54: 24.14 | E54: 386.88 | F54: 386.88 | G54: 24.42 | H54: 24.24
A55: Intangible Assets - excluding Goodwill - Net - Total | B55: 11.67 | C55: 0 | D55: 21.96 | E55: 71.3 | F55: 80.08 | H55: 0
A56: Brands, Patents, Trademarks, Marketing & Artistic Intangibles - Net | C56: 0 | D56: 19.54 | E56: 44.41 | F56: 49.21
A57: Licenses, Franchises, Copyrights, Property Rights, Prototypes, Contract Based, Models & Designs - Net | B57: 11.67
A58: Intangible Assets - Other - Net | B58: 0 | C58: 0 | D58: 2.42 | E58: 26.89 | F58: 30.88
A59: Total Non-Current Assets | B59: 3622.99 | C59: 3031.36 | D59: 2447.59 | E59: 2327.63 | F59: 2060.84 | G59: 1473.42 | H59: 655.43
A60: Total Assets
A61: Total Assets | B61: 7603.29 | C61: 7091.94 | D61: 5607.04 | E61: 4942.48 | F61: 4185.22 | G61: 3281.35 | H61: 2084.71
A62: Current Liabilities
A63: Trade Accounts Payable & Accruals - Short-Term | B63: 886.88 | C63: 958.6 | D63: 738.97 | E63: 764.77 | F63: 477.96 | G63: 317.37 | H63: 310.96
A64: Trade Accounts & Trade Notes Payable - Short-Term | B64: 271.41 | C64: 348.44 | D64: 172.73 | E64: 289.73 | F64: 172.25 | G64: 80 | H64: 95.53
A65: Accrued Expenses - Short-Term | B65: 615.48 | C65: 610.16 | D65: 566.24 | E65: 475.05 | F65: 305.71 | G65: 237.37 | H65: 215.42
A66: Short-Term Debt & Current Portion of Long-Term Debt | B66: 12.4 | C66: 10.8 | D66: 8.6 | E66: 4
A67: Short-Term Debt & Notes Payable | B67: 12.4 | C67: 10.8 | D67: 8.6 | E67: 4
A68: Derivative Liabilities - Hedging - Short-Term | B68: 74.64 | C68: 2.87 | D68: 25.63 | E68: 18.99 | F68: 18.77 | G68: 1.92 | H68: 1.04
A69: Income Taxes - Payable - Short-Term | B69: 183.13 | C69: 12.1 | D69: 174.22 | E69: 133.85 | F69: 8.36 | G69: 26.44 | H69: 67.41
A70: Operating Lease Liabilities - Current Portion/Short-Term | B70: 275.15 | C70: 249.27 | D70: 207.97 | E70: 189 | F70: 166.09 | G70: 128.5
A71: Other Current Liabilities - Total | B71: 407.43 | C71: 397.62 | D71: 336.81 | E71: 294.73 | F71: 212.01 | G71: 146.2 | H71: 121.07
A72: Deferred Income - Short-Term | G72: 12.71 | H72: 8.05
A73: Provisions - Short-Term | B73: 73.89 | C73: 61.63 | D73: 55.53 | E73: 41.69 | F73: 32.56 | G73: 12.9 | H73: 11.32
A74: Other Current Liabilities | B74: 333.54 | C74: 335.99 | D74: 281.28 | E74: 253.04 | F74: 179.45 | G74: 120.6 | H74: 101.71
A75: Total Current Liabilities | B75: 1839.63 | C75: 1631.26 | D75: 1492.2 | E75: 1405.33 | F75: 883.18 | G75: 620.42 | H75: 500.48
A76: Non-Current Liabilities
A77: Deferred Tax & Investment Tax Credits - Long-Term | B77: 98.19 | C77: 29.52 | D77: 55.08 | E77: 53.35 | F77: 58.76 | G77: 43.43 | H77: 14.25
A78: Deferred Tax - Liability - Long-Term | B78: 98.19 | C78: 29.52 | D78: 55.08 | E78: 53.35 | F78: 58.76 | G78: 43.43 | H78: 14.25
A79: Operating Lease Liabilities - Long-Term | B79: 1300.64 | C79: 1154.01 | D79: 862.36 | E79: 692.06 | F79: 632.59 | G79: 611.46
A80: Other Non-Current Liabilities - Total | B80: 40.79 | C80: 45.07 | D80: 48.6 | E80: 51.69 | F80: 52.13 | G80: 53.82 | H80: 124.01
A81: Other Non-Current Liabilities | B81: 40.79 | C81: 45.07 | D81: 48.6 | E81: 51.69 | F81: 52.13 | G81: 53.82 | H81: 124.01
A82: Total Non-Current Liabilities | B82: 1439.62 | C82: 1228.6 | D82: 966.04 | E82: 797.1 | F82: 743.47 | G82: 708.72 | H82: 138.26
A83: Total Liabilities
A84: Total Liabilities | B84: 3279.25 | C84: 2859.86 | D84: 2458.24 | E84: 2202.43 | F84: 1626.65 | G84: 1329.14 | H84: 638.74
A85: Shareholders' Equity
A86: Shareholders' Equity - Attributable to Parent Shareholders - Total | B86: 4324.05 | C86: 4232.08 | D86: 3148.8 | E86: 2740.05 | F86: 2558.57 | G86: 1952.22 | H86: 1445.98
A87: Preferred Shareholders Equity | B87: 0 | C87: 0 | D87: 0 | E87: 0 | F87: 0 | G87: 0 | H87: 0
A88: Preferred Stock - Non-Redeemable | B88: 0 | C88: 0 | D88: 0 | E88: 0 | F88: 0 | G88: 0 | H88: 0
A89: Common Equity Attributable to Parent Shareholders | B89: 4324.05 | C89: 4232.08 | D89: 3148.8 | E89: 2740.05 | F89: 2558.57 | G89: 1952.22 | H89: 1445.98
A90: Common Equity - Contributed | B90: 638.77 | C90: 575.98 | D90: 475.26 | E90: 423.12 | F90: 389.29 | G90: 356.16 | H90: 315.89
A91: Common Stock - Issued & Paid | B91: 0.58 | C91: 0.61 | D91: 0.61 | E91: 0.62 | F91: 0.63 | G91: 0.62 | H91: 0.61
A92: Common Stock - Additional Paid in Capital including Option Reserve | B92: 638.19 | C92: 575.37 | D92: 474.65 | E92: 422.51 | F92: 388.67 | G92: 355.54 | H92: 315.29
A93: Equity - Non-Contributed - Reserves & Retained Earnings | B93: 3685.28 | C93: 3656.11 | D93: 2673.54 | E93: 2316.92 | F93: 2169.27 | G93: 1596.06 | H93: 1130.08
A94: Retained Earnings - Total | B94: 4109.72 | C94: 3920.36 | D94: 2926.13 | E94: 2512.84 | F94: 2346.43 | G94: 1820.64 | H94: 1346.89
A95: Comprehensive Income - Accumulated - Total | B95: -424.44 | C95: -264.26 | D95: -252.58 | E95: -195.92 | F95: -177.15 | G95: -224.58 | H95: -216.81
A96: Other Reserves/Equity - Total | B96: 0
A97: Common Equity - Total | B97: 4324.05 | C97: 4232.08 | D97: 3148.8 | E97: 2740.05 | F97: 2558.57 | G97: 1952.22 | H97: 1445.98
A98: Total Shareholders' Equity
A99: Total Shareholders' Equity - including Minority Interest & Hybrid Debt | B99: 4324.05 | C99: 4232.08 | D99: 3148.8 | E99: 2740.05 | F99: 2558.57 | G99: 1952.22 | H99: 1445.98
A100: Total Liabilities & Shareholders' Equity
A101: Total Liabilities & Equity | B101: 7603.29 | C101: 7091.94 | D101: 5607.04 | E101: 4942.48 | F101: 4185.22 | G101: 3281.35 | H101: 2084.71
...

Sheet Cash Flow
A1: Company Fundamentals - Cash Flow
A2: Company Name | B2: Lululemon Athletica Inc (LULU.O)
A3: Country of Exchange | B3: United States of America
A4: Country of Headquarters | B4: Canada
A5: TRBC Industry Group | B5: Textiles & Apparel
A6: CF Template | B6: IND
A7: Consolidation Basis | B7: Consolidated
A8: Scaling | B8: Millions
A9: Period | B9: Annual
A10: Export Date | B10: 45922.395
A11: Statement Data | B11: 2025 | C11: 2024 | D11: 2023 | E11: 2022 | F11: 2021 | G11: 2020 | H11: 2019
A12: Period End Date | B12: 45690 | C12: 45319 | D12: 44955 | E12: 44591 | F12: 44227 | G12: 43863 | H12: 43499
A13: Statement Date | B13: 45690 | C13: 45319 | D13: 44955 | E13: 44591 | F13: 44227 | G13: 43863 | H13: 43499
A14: Standardized Currency | B14: USD | C14: USD | D14: USD | E14: USD | F14: USD | G14: USD | H14: USD
A15: Template Type | B15: Industrial - Indirect | C15: Industrial - Indirect | D15: Industrial - Indirect | E15: Industrial - Indirect | F15: Industrial - Indirect | G15: Industrial - Indirect | H15: Industrial - Indirect
A17: Cash Flow - Standardized (Currency: Standardized)
A18: Field Name | B18: 02-02-2025 | C18: 28-01-2024 | D18: 29-01-2023 | E18: 30-01-2022 | F18: 31-01-2021 | G18: 02-02-2020 | H18: 03-02-2019
A19: Operating Cash Flow - Indirect
A20: Profit/(Loss) - Starting Line - Cash Flow | B20: 1814.62 | C20: 1550.19 | D20: 854.8 | E20: 975.32 | F20: 588.91 | G20: 645.6 | H20: 483.8
A21: Non-cash Items & Reconciliation Adjustments - Cash Flow | B21: 509.99 | C21: 546.75 | D21: 708.66 | E21: 284.65 | F21: 261.97 | G21: 217.79 | H21: 146.1
A22: Other Non-Cash Items & Reconciliation Adjustments - Cash Flow - to Reconcile | B22: -36.23 | C22: -4.84 | D22: -23.34 | E22: -18.7 | F22: -13.7 | G22: -11.94 | H22: -6.86
A23: Depreciation, Depletion & Amortization including Impairment - Cash Flow - to Reconcile | B23: 446.52 | C23: 453.89 | D23: 699.7 | E23: 224.21 | F23: 185.48 | G23: 161.93 | H23: 122.48
A24: Depreciation & Depletion - Property, Plant & Equipment - Cash Flow - to Reconcile | B24: 446.52 | C24: 379.38 | D24: 291.79 | E24: 224.21 | F24: 185.48 | G24: 161.93 | H24: 122.48
A25: Impairment - Property, Plant & Equipment including Intangible Assets - Cash Flow - to Reconcile | C25: 74.5 | D25: 407.91
A26: Deferred Income Taxes & Income Tax Credits - Cash Flow - to Reconcile | B26: 57.45 | C26: -28.38 | D26: 3.04 | E26: -5.18 | F26: 34.91 | G26: 24.13 | H26: 16.79
A27: Assets Sale - Gain/(Loss) - Cash Flow - to Reconcile | D27: -10.18
A28: Financial Assets - Unrealized Gain/(Loss) - Cash Flow - to Reconcile | B28: -47.76 | C28: 32.53 | D28: -38.65 | E28: 15.19 | F28: 4.49 | G28: -1.92 | H28: -14.88
A29: Share Based Payments - Cash Flow - to Reconcile | B29: 90.01 | C29: 93.56 | D29: 78.08 | E29: 69.14 | F29: 50.8 | G29: 45.59 | H29: 28.57
A30: Cash Flow from Operating Activities before Changes in Working Capital | B30: 2324.61 | C30: 2096.94 | D30: 1563.46 | E30: 1259.98 | F30: 850.89 | G30: 863.39 | H30: 629.9
A31: Working Capital - Increase/(Decrease) - Cash Flow | B31: -51.89 | C31: 199.22 | D31: -596.99 | E31: 129.13 | F31: -47.55 | G31: -194.07 | H31: 112.88
A32: Accounts Receivables - Decrease/(Increase) - Cash Flow | B32: 1.63
A33: Inventories - Decrease/(Increase) - Cash Flow | B33: -156.08 | C33: 66.58 | D33: -510.51 | E33: -323.61 | F33: -96.55 | G33: -117.59 | H33: -85.94
A34: Prepaid Expenses - Decrease/(Increase) - Cash Flow | B34: -73.82 | C34: 49.08 | D34: -180.53 | E34: -62.3 | F34: -124.96 | G34: -117.38 | H34: -31.09
A35: Other Assets - Decrease/(Increase) - Cash Flow | B35: -73.2 | C35: -53.28 | D35: -36.52 | E35: -17.56 | F35: -49.06
A36: Accounts Payable - Increase/(Decrease) - Cash Flow | B36: -57.04 | C36: 177.37 | D36: -107.28 | E36: 117.66 | F36: 82.66 | G36: -14.81 | H36: 71.96
A37: Accrued Expenses - Increase/(Decrease) - Cash Flow | B37: 81.03 | C37: -1.41 | D37: 112.62 | E37: 179.15 | F37: 92.47 | G37: 15.73 | H37: 45.91
A38: Taxes Payable - Increase/(Decrease) - Cash Flow | B38: 157.21 | C38: -173.2 | D38: 35.99 | E38: 120.78 | F38: -24.12 | G38: -34.14 | H38: 46.43
A39: Other Liabilities - Increase/(Decrease) -Total - Cash Flow | B39: 44.9 | C39: 96.55 | D39: 65.34 | E39: 101.51 | F39: 58.75 | G39: 56.7 | H39: 65.61
A40: Other Assets & Liabilities - Increase/(Decrease) - Net - Cash Flow | B40: 23.5 | C40: 37.53 | D40: 23.91 | E40: 13.49 | F40: 13.27 | G40: 17.42
A41: Net Cash Flow from Operating Activities | B41: 2272.71 | C41: 2296.16 | D41: 966.46 | E41: 1389.11 | F41: 803.34 | G41: 669.32 | H41: 742.78
A42: Investing Cash Flow
A43: Capital Expenditures - Net - Cash Flow | B43: 689.23 | C43: 651.87 | D43: 638.66 | E43: 394.5 | F43: 229.23 | G43: 283.05 | H43: 225.81
A44: Property, Plant & Equipment - Purchased/(Sold) - Net - Cash Flow | B44: 689.23 | C44: 651.87 | D44: 638.66 | E44: 394.5 | F44: 229.23 | G44: 283.05 | H44: 225.81
A45: Property, Plant & Equipment - Purchased - Cash Flow | B45: 689.23 | C45: 651.87 | D45: 638.66 | E45: 394.5 | F45: 229.23 | G45: 283.05 | H45: 225.81
A46: Capital Expenditures - Total | B46: 689.23 | C46: 651.87 | D46: 638.66 | E46: 394.5 | F46: 229.23 | G46: 283.05 | H46: 225.81
A47: Acquisition & Disposals of Business - Assets - Sold/(Acquired) - Net - Cash Flow | B47: -154.15 | F47: -452.58
A48: Acquisition of Business - Cash Flow | B48: 154.15 | F48: 452.58
A49: Derivative Financial Instruments - Hedging - Sold/(Purchased) -Total - Cash Flow | B49: 50.21 | C49: -1.61 | D49: 47.8 | E49: -23.39 | F49: -14.61 | G49: 0.35 | H49: -16.22
A50: Other Investing Cash Flow - Decrease/(Increase) | B50: -5.01 | C50: -0.66 | D50: 20.92 | E50: -10 | F50: 0.88 | G50: 4.29 | H50: -0.77
A51: Net Cash Flow from Investing Activities | B51: -798.17 | C51: -654.13 | D51: -569.94 | E51: -427.89 | F51: -695.53 | G51: -278.41 | H51: -242.79
A52: Financing Cash Flow
A53: Stock - Total - Issuance/(Retirement) - Net - Cash Flow | B53: -1636.88 | C53: -558.65 | D53: -444 | E53: -812.6 | F53: -63.66 | G53: -173.4 | H53: -598.34
A54: Stock - Issuance/(Retirement) - Net - Excluding Options/Warrants - Cash Flow | B54: -1636.88 | C54: -558.65 | D54: -444 | E54: -812.6 | F54: -63.66 | G54: -173.4 | H54: -598.34
A55: Stock - Common - Issuance/(Retirement) - Net - Cash Flow | B55: -1636.88 | C55: -558.65 | D55: -444 | E55: -812.6 | F55: -63.66 | G55: -173.4 | H55: -598.34
A56: Stock - Common - Repurchased/Retired - Cash Flow | B56: 1636.88 | C56: 558.65 | D56: 444 | E56: 812.6 | F56: 63.66 | G56: 173.4 | H56: 598.34
A57: Other Financing Cash Flow - Increase/(Decrease) | B57: -15.63 | C57: 9.82 | D57: -23.49 | E57: -32.38 | F57: -17.12 | G57: -3.77 | H57: 8.13
A58: Net Cash Flow from Financing Activities | B58: -1652.51 | C58: -548.83 | D58: -467.49 | E58: -844.99 | F58: -80.79 | G58: -177.17 | H58: -590.21
A59: Foreign Exchange Effects
A60: Foreign Exchange Effects - Cash Flow | B60: -81.67 | C60: -4.1 | D60: -34.04 | E60: -6.88 | F60: 30 | G60: -1.55 | H60: -18.95
A61: Change in Cash
A62: Net Change in Cash - Total | B62: -259.63 | C62: 1089.1 | D62: -105 | E62: 109.35 | F62: 57.01 | G62: 212.19 | H62: -109.18
A63: Net Cash from Continuing Operations | B63: -259.63 | C63: 1089.1 | D63: -105 | E63: 109.35 | F63: 57.01 | G63: 212.19 | H63: -109.18
A64: Net Cash - Beginning Balance | B64: 2243.97 | C64: 1154.87 | D64: 1259.87 | E64: 1150.52 | F64: 1093.51 | G64: 881.32 | H64: 990.5
A65: Net Cash - Ending Balance | B65: 1984.34 | C65: 2243.97 | D65: 1154.87 | E65: 1259.87 | F65: 1150.52 | G65: 1093.51 | H65: 881.32
A66: Supplemental
A67: Income Taxes - Paid/(Reimbursed) - Cash Flow - Supplemental | B67: 579.18 | C67: 824.21 | D67: 502.14 | E67: 245.21 | F67: 260.89 | G67: 305.49 | H67: 177.04
A68: Interest Paid - Cash Flow - Supplemental | B68: 0.48 | C68: 0.23 | D68: 0.12 | E68: 0.01 | F68: 0.11 | G68: 0.33 | H68: 1.39
A69: CF from Optg Activities before Change in WC & Int Payments | B69: 2324.61 | C69: 2096.94 | D69: 1563.46 | E69: 1259.98 | F69: 850.89 | G69: 863.39 | H69: 629.9
A70: Common Stock Buyback - Net | B70: 1636.88 | C70: 558.65 | D70: 444 | E70: 812.6 | F70: 63.66 | G70: 173.4 | H70: 598.34
A71: Depreciation, Depletion & Amortization - Cash Flow | B71: 446.52 | C71: 379.38 | D71: 291.79 | E71: 224.21 | F71: 185.48 | G71: 161.93 | H71: 122.48
A72: Free Cash Flow to Equity | B72: 1583.48 | C72: 1644.3 | D72: 327.81 | E72: 994.61 | F72: 574.11 | G72: 386.27 | H72: 516.97
A73: Free Cash Flow Net of Dividends | B73: 1583.48 | C73: 1644.3 | D73: 327.81 | E73: 994.61 | F73: 574.11 | G73: 386.27 | H73: 516.97
A74: Free Cash Flow | B74: 1583.48 | C74: 1644.3 | D74: 327.81 | E74: 994.61 | F74: 574.11 | G74: 386.27 | H74: 516.97
A75: Dividends Provided/Paid - Common

Sheet Pension
A1: Company Fundamentals - Pension
A2: Company Name | B2: Lululemon Athletica Inc (LULU.O)
A3: Country of Exchange | B3: United States of America
A4: Country of Headquarters | B4: Canada
A5: TRBC Industry Group | B5: Textiles & Apparel
A6: CF Template | B6: IND
A7: Consolidation Basis | B7: Consolidated
A8: Scaling | B8: Millions
A9: Period | B9: Annual
A10: Export Date | B10: 45922.395
A11: Statement Data | B11: 2025 | C11: 2024 | D11: 2023 | E11: 2022 | F11: 2021 | G11: 2020 | H11: 2019
A12: Period End Date | B12: 45690 | C12: 45319 | D12: 44955 | E12: 44591 | F12: 44227 | G12: 43863 | H12: 43499
A13: Statement Date | B13: 45690 | C13: 45319 | D13: 44955 | E13: 44591 | F13: 44227 | G13: 43863 | H13: 43499
A14: Standardized Currency | B14: USD | C14: USD | D14: USD | E14: USD | F14: USD | G14: USD | H14: USD
A15: Template Type | B15: Industrial | C15: Industrial | D15: Industrial | E15: Industrial | F15: Industrial | G15: Industrial | H15: Industrial
A17: Pension - Standardized (Currency: Standardized)
A18: Field Name | B18: 02-02-2025 | C18: 28-01-2024 | D18: 29-01-2023 | E18: 30-01-2022 | F18: 31-01-2021 | G18: 02-02-2020 | H18: 03-02-2019
A19: Income/Expense
A20: Total Pension Plans - Total Pension & Post-Retirement | B20: 22.2 | C20: 19.8 | D20: 14 | E20: 11.8 | F20: 9.2 | G20: 8.5 | H20: 6.4
A21: Total Pension Plan Expense - Total | B21: 22.2 | C21: 19.8 | D21: 14 | E21: 11.8 | F21: 9.2 | G21: 8.5 | H21: 6.4
A22: Total Pension Plans - Domestic | B22: 22.2 | C22: 19.8 | D22: 14 | E22: 11.8 | F22: 9.2 | G22: 8.5 | H22: 6.4
A23: Defined Contribution Expense - Total Pension & Post-Retirement | B23: 22.2 | C23: 19.8 | D23: 14 | E23: 11.8 | F23: 9.2 | G23: 8.5 | H23: 6.4
A24: Defined Contribution Expense - Total Pension | B24: 22.2 | C24: 19.8 | D24: 14 | E24: 11.8 | F24: 9.2 | G24: 8.5 | H24: 6.4
A25: Defined Contribution Expense - Domestic | B25: 22.2 | C25: 19.8 | D25: 14 | E25: 11.8 | F25: 9.2 | G25: 8.5 | H25: 6.4

Sheet Financial Summary
A1: Company Fundamentals - Financial Summary
A2: Company Name | B2: Lululemon Athletica Inc (LULU.O)
A3: Country of Exchange | B3: United States of America
A4: Country of Headquarters | B4: Canada
A5: TRBC Industry Group | B5: Textiles & Apparel
A6: CF Template | B6: IND
A7: Consolidation Basis | B7: Consolidated
A8: Scaling | B8: Millions
A9: Period | B9: Annual
A10: Export Date | B10: 45922.395
A11: Statement Data | B11: 2025 | C11: 2024 | D11: 2023 | E11: 2022 | F11: 2021 | G11: 2020 | H11: 2019
A12: Period End Date | B12: 45690 | C12: 45319 | D12: 44955 | E12: 44591 | F12: 44227 | G12: 43863 | H12: 43499
A13: Statement Date | B13: 45690 | C13: 45319 | D13: 44955 | E13: 44591 | F13: 44227 | G13: 43863 | H13: 43499
A14: Standardized Currency | B14: USD | C14: USD | D14: USD | E14: USD | F14: USD | G14: USD | H14: USD
A15: Template Type | B15: Industrial - Gross Profit | C15: Industrial - Gross Profit | D15: Industrial - Gross Profit | E15: Industrial - Gross Profit | F15: Industrial - Gross Profit | G15: Industrial - Gross Profit | H15: Industrial - Gross Profit
A17: Financial Summary - Standardized (Currency: Standardized)
A18: Field Name | B18: 02-02-2025 | C18: 28-01-2024 | D18: 29-01-2023 | E18: 30-01-2022 | F18: 31-01-2021 | G18: 02-02-2020 | H18: 03-02-2019
A19: Selected Income Statement Items
A20: Revenue from Business Activities - Total | B20: 10588.13 | C20: 9619.28 | D20: 8110.52 | E20: 6256.62 | F20: 4401.88 | G20: 3979.3 | H20: 3288.32
A21: Gross Profit - Industrials/Property - Total | B21: 6268.08 | C21: 5604.4 | D21: 4483.59 | E21: 3599.78 | F21: 2458.83 | G21: 2223.39 | H21: 1816.29
A22: Operating Profit before Non-Recurring Income/Expense | B22: 2509.2 | C22: 2207.18 | D22: 1726.14 | E22: 1374.75 | F22: 849.83 | G22: 890.62 | H22: 704.44
A23: Earnings before Interest, Taxes, Depreciation & Amortization (EBITDA) | B23: 2955.72 | C23: 2586.56 | D23: 2017.93 | E23: 1598.96 | F23: 1035.31 | G23: 1052.55 | H23: 826.93
A24: Income before Discontinued Operations & Extraordinary Items | B24: 1814.62 | C24: 1550.19 | D24: 854.8 | E24: 975.32 | F24: 588.91 | G24: 645.6 | H24: 491.27
A25: Selected Balance Sheet Items
A26: Cash & Cash Equivalents | B26: 1984.34 | C26: 2243.97 | D26: 1154.87 | E26: 1259.87 | F26: 1150.52 | G26: 1093.51 | H26: 881.32
A27: Cash & Short-Term Investments | B27: 1984.34 | C27: 2243.97 | D27: 1154.87 | E27: 1259.87 | F27: 1150.52 | G27: 1093.51 | H27: 881.32
A28: Total Assets | B28: 7603.29 | C28: 7091.94 | D28: 5607.04 | E28: 4942.48 | F28: 4185.22 | G28: 3281.35 | H28: 2084.71
A29: Debt - Total | B29: 12.4 | C29: 10.8 | D29: 8.6 | E29: 4
A30: Common Equity - Total | B30: 4324.05 | C30: 4232.08 | D30: 3148.8 | E30: 2740.05 | F30: 2558.57 | G30: 1952.22 | H30: 1445.98
A31: Selected Cash Flow Items
A32: Net Cash Flow from Operating Activities | B32: 2272.71 | C32: 2296.16 | D32: 966.46 | E32: 1389.11 | F32: 803.34 | G32: 669.32 | H32: 742.78
A33: Depreciation, Depletion & Amortization including Impairment - Cash Flow - to Reconcile | B33: 446.52 | C33: 453.89 | D33: 699.7 | E33: 224.21 | F33: 185.48 | G33: 161.93 | H33: 122.48
A34: Capital Expenditures - Net - Cash Flow | B34: 689.23 | C34: 651.87 | D34: 638.66 | E34: 394.5 | F34: 229.23 | G34: 283.05 | H34: 225.81
A35: Net Change in Cash - Total | B35: -259.63 | C35: 1089.1 | D35: -105 | E35: 109.35 | F35: 57.01 | G35: 212.19 | H35: -109.18
A36: Free Cash Flow Net of Dividends | B36: 1583.48 | C36: 1644.3 | D36: 327.81 | E36: 994.61 | F36: 574.11 | G36: 386.27 | H36: 516.97
A37: Selected Per Share Data
A38: Dividend Yield - Common Stock - Gross - Issue Specific - %
A39: Dividend Yield - Common Stock - Net - Issue Specific - %
A40: EPS - Diluted - excluding Extraordinary Items Applicable to Common - Total | B40: 14.64 | C40: 12.2 | D40: 6.68 | E40: 7.49 | F40: 4.5 | G40: 4.93 | H40: 3.67
A41: Shares used to calculate Diluted EPS - Total | B41: 123.94 | C41: 127.06 | D41: 128.02 | E41: 130.29 | F41: 130.87 | G41: 130.96 | H41: 133.97
A42: Company Reported Non-GAAP Measures
A43: Non-GAAP Revenues - Company Reported | D43: 2001.63 | E43: 1759.24
A44: Non-GAAP Income from Operations - Company Reported | C44: 2230.89 | H44: 705.84
A45: Non-GAAP EPS Diluted - Company Reported | G45: 3.84 | H45: 3.84
A46: Non-GAAP Operating Margin % - Company Reported | C46: 23.2 | H46: 21.5
A47: Profitability / Return
A48: Gross Profit Margin - % | B48: 59.2 | C48: 58.26 | D48: 55.28 | E48: 57.54 | F48: 55.86 | G48: 55.87 | H48: 55.23
A49: EBITDA Margin - % | B49: 27.92 | C49: 26.89 | D49: 24.88 | E49: 25.56 | F49: 23.52 | G49: 26.45 | H49: 25.15
A50: Operating Margin - % | B50: 23.7 | C50: 22.95 | D50: 21.28 | E50: 21.97 | F50: 19.31 | G50: 22.38 | H50: 21.42
A51: Income before Tax Margin - % | B51: 24.33 | C51: 22.62 | D51: 16.43 | E51: 21.32 | F51: 18.61 | G51: 22.55 | H51: 21.75
A52: Income Tax Rate - % | B52: 29.56 | C52: 28.75 | D52: 35.85 | E52: 26.88 | F52: 28.12 | G52: 28.06 | H52: 31.32
A53: Net Margin - % | B53: 17.14 | C53: 16.12 | D53: 10.54 | E53: 15.59 | F53: 13.38 | G53: 16.22 | H53: 14.94
A54: Free Cash Flow | B54: 1583.48 | C54: 1644.3 | D54: 327.81 | E54: 994.61 | F54: 574.11 | G54: 386.27 | H54: 516.97
A55: Return on Average Common Equity - % (Income available to Common excluding Extraordinary Items) | B55: 42.42 | C55: 42.01 | D55: 29.03 | E55: 36.81 | F55: 26.11 | G55: 38 | H55: 32.29
A56: Return on Average Total Assets - % (Income before Discontinued Operations & Extraordinary Items) | B56: 24.7 | C56: 24.41 | D56: 16.21 | E56: 21.37 | F56: 15.77 | G56: 24.06 | H56: 24.06
A57: Return on Invested Capital - % | B57: 42.3 | C57: 41.9 | D57: 27.49 | E57: 35.8 | F57: 25.36 | G57: 38 | H57: 31.8
A58: Growth
A59: Revenue from Business Activities - Total | B59: 10588.13 | C59: 9619.28 | D59: 8110.52 | E59: 6256.62 | F59: 4401.88 | G59: 3979.3 | H59: 3288.32
A60: Operating Profit before Non-Recurring Income/Expense | B60: 2509.2 | C60: 2207.18 | D60: 1726.14 | E60: 1374.75 | F60: 849.83 | G60: 890.62 | H60: 704.44
A61: Earnings before Interest, Taxes, Depreciation & Amortization (EBITDA) | B61: 2955.72 | C61: 2586.56 | D61: 2017.93 | E61: 1598.96 | F61: 1035.31 | G61: 1052.55 | H61: 826.93
A62: Income before Discontinued Operations & Extraordinary Items | B62: 1814.62 | C62: 1550.19 | D62: 854.8 | E62: 975.32 | F62: 588.91 | G62: 645.6 | H62: 491.27
A63: EPS - Diluted - excluding Extraordinary Items Applicable to Common - Total | B63: 14.64 | C63: 12.2 | D63: 6.68 | E63: 7.49 | F63: 4.5 | G63: 4.93 | H63: 3.67
A64: Common Shares - Outstanding - Total | B64: 126.4 | C64: 131.34 | D64: 132.44 | E64: 133.7 | F64: 135.56 | G64: 136.58 | H64: 140.26
A65: Financial Strength / Leverage
A66: Total Debt Percentage of Total Assets | B66: 0.16 | C66: 0.15 | D66: 0.15 | E66: 0.08
A67: Total Debt Percentage of Total Capital | B67: 0.29 | C67: 0.25 | D67: 0.27 | E67: 0.15
A68: Total Debt Percentage of Total Equity | B68: 0.29 | C68: 0.26 | D68: 0.27 | E68: 0.15
A69: Debt Service | D69: -61.6 | E69: -35.8 | F69: -23.5 | G69: -0.02 | H69: -0.01
A70: Debt Service Percentage of Normalized after Tax Profit
A71: Earnings Retention Rate | B71: 1 | C71: 1 | D71: 1 | E71: 1 | F71: 1 | G71: 1 | H71: 1
A72: Dividend Payout Ratio - %
A73: Enterprise Value Breakdown
A74: Market Capitalization | B74: 50442.74 | C74: 60322.96 | D74: 39665.02 | E74: 40845.24 | F74: 42839.51 | G74: 31191.3 | H74: 19346.87
A75: Debt - Total | B75: 12.4 | C75: 10.8 | D75: 8.6 | E75: 4
A76: Preferred Shareholders Equity
A77: Cash & Short Term Investments - Total | B77: 1984.34 | C77: 2243.97 | D77: 1154.87 | E77: 1259.87 | F77: 1150.52 | G77: 1093.51 | H77: 881.32
A78: Enterprise Value | B78: 48470.8 | C78: 58089.79 | D78: 38518.75 | E78: 39589.37 | F78: 41688.99 | G78: 30097.79 | H78: 18465.55
A79: Dupont / Earning Power
A80: Asset Turnover | B80: 1.44 | C80: 1.51 | D80: 1.54 | E80: 1.37 | F80: 1.18 | G80: 1.48 | H80: 1.61
A81: Income before Tax Margin - % | B81: 24.33 | C81: 22.62 | D81: 16.43 | E81: 21.32 | F81: 18.61 | G81: 22.55 | H81: 21.75
A82: Pretax ROA - % | B82: 35.06 | C82: 34.27 | D82: 25.26 | E82: 29.23 | F82: 21.95 | G82: 33.45 | H82: 35.03
A83: Total Assets to Total Shareholders Equity - including Minority Interest & Hybrid Debt | B83: 1.72 | C83: 1.72 | D83: 1.79 | E83: 1.72 | F83: 1.66 | G83: 1.58 | H83: 1.34
A84: Pretax ROE - % | B84: 60.22 | C84: 58.96 | D84: 45.26 | E84: 50.35 | F84: 36.33 | G84: 52.82 | H84: 47.01
A85: Tax Complement | B85: 0.7 | C85: 0.71 | D85: 0.64 | E85: 0.73 | F85: 0.72 | G85: 0.72 | H85: 0.69
A86: Return on Average Common Equity - % (Income available to Common excluding Extraordinary Items) | B86: 42.42 | C86: 42.01 | D86: 29.03 | E86: 36.81 | F86: 26.11 | G86: 38 | H86: 32.29
A87: Earnings Retention Rate | B87: 1 | C87: 1 | D87: 1 | E87: 1 | F87: 1 | G87: 1 | H87: 1
A88: Reinvestment Rate - % | B88: 42.42 | C88: 42.01 | D88: 29.03 | E88: 36.81 | F88: 26.11 | G88: 38 | H88: 32.29
A89: Productivity
A90: Net Income after Tax per Employee | B90: 47132.88 | C90: 43060.83 | D90: 27136.51 | E90: 36123.04 | F90: 26768.77 | G90: 37210.14 | H90: 33763.92
A91: Sales per Employee | B91: 275016.26 | C91: 267202.17 | D91: 257476.76 | E91: 231726.56 | F91: 200085.41 | G91: 229354.24 | H91: 226001.31
A92: Total Assets per Employee | B92: 194956.21 | C92: 186630.03 | D92: 164912.88 | E92: 170430.28 | F92: 167408.6 | G92: 172702.84 | H92: 132784.14
A93: Liquidity
A94: Current Ratio | B94: 2.16 | C94: 2.49 | D94: 2.12 | E94: 1.86 | F94: 2.41 | G94: 2.91 | H94: 2.86
A95: Quick Ratio | B95: 1.38 | C95: 1.68 | D95: 1.15 | E95: 1.17 | F95: 1.67 | G95: 2.08 | H95: 2.05
A96: Working Capital to Total Assets | B96: 0.28 | C96: 0.34 | D96: 0.3 | E96: 0.24 | F96: 0.3 | G96: 0.36 | H96: 0.45
A97: Operating
A98: Accounts Receivable Turnover | B98: 86.45 | C98: 74.66 | D98: 77.28 | E98: 81.94 | F98: 75.94 | G98: 104.71 | H98: 119.66
A99: Average Receivables Collection Days | B99: 4.31 | C99: 4.9 | D99: 4.74 | E99: 4.47 | F99: 4.82 | G99: 3.5 | H99: 3.12
A100: Payables Turnover | B100: 13.94 | C100: 15.41 | D100: 15.69 | E100: 11.5 | F100: 15.41 | G100: 20.01 | H100: 24.5
A101: Average Payables Payment Days | B101: 26.76 | C101: 23.76 | D101: 23.33 | E101: 31.82 | F101: 23.76 | G101: 18.29 | H101: 15.23
...

Sheet Valuation
A1: Company Fundamentals - Valuation
A2: Company Name | B2: Lululemon Athletica Inc (LULU.O)
A3: Country of Exchange | B3: United States of America
A4: Country of Headquarters | B4: Canada
A5: TRBC Industry Group | B5: Textiles & Apparel
A6: CF Template | B6: IND
A7: Consolidation Basis | B7: Consolidated
A8: Scaling | B8: Millions
A9: Period | B9: Annual
A10: Export Date | B10: 45922.395
A11: Statement Data | B11: 2025 | C11: 2024 | D11: 2023 | E11: 2022 | F11: 2021 | G11: 2020 | H11: 2019
A12: Period End Date | B12: 45690 | C12: 45319 | D12: 44955 | E12: 44591 | F12: 44227 | G12: 43863 | H12: 43499
A13: Statement Date | B13: 45690 | C13: 45319 | D13: 44955 | E13: 44591 | F13: 44227 | G13: 43863 | H13: 43499
A14: Standardized Currency | B14: USD | C14: USD | D14: USD | E14: USD | F14: USD | G14: USD | H14: USD
A15: Template Type | B15: Industrial - Gross Profit | C15: Industrial - Gross Profit | D15: Industrial - Gross Profit | E15: Industrial - Gross Profit | F15: Industrial - Gross Profit | G15: Industrial - Gross Profit | H15: Industrial - Gross Profit
A17: Valuation - Standardized (Currency: Standardized)
A18: Field Name | B18: 02-02-2025 | C18: 28-01-2024 | D18: 29-01-2023 | E18: 30-01-2022 | F18: 31-01-2021 | G18: 02-02-2020 | H18: 03-02-2019
A19: Enterprise Value
A20: Enterprise Value | B20: 48470.8 | C20: 58089.79 | D20: 38518.75 | E20: 39589.37 | F20: 41688.99 | G20: 30097.79 | H20: 18465.55
A21: Enterprise Value, 5 Year Average | B21: 45271.54 | C21: 41596.94 | D21: 33672.09 | E21: 27911.41 | F21: 21678.51 | G21: 14960.42 | H21: 10689.08
A22: Market Capitalization
A23: Market Capitalization | B23: 50442.74 | C23: 60322.96 | D23: 39665.02 | E23: 40845.24 | F23: 42839.51 | G23: 31191.3 | H23: 19346.87
A24: Market Capitalization, 5 Year Average | B24: 46823.09 | C24: 42972.81 | D24: 34777.59 | E24: 28985.75 | F24: 22648.64 | G24: 15800.75 | H24: 11443.6
A25: Price Close
A26: Price Close (End of Period) | B26: 414.2 | C26: 478.03 | D26: 310.85 | E26: 315.91 | F26: 328.68 | G26: 239.39 | H26: 146.12
A27: Price Close (End of Period), 5 Year Average | B27: 369.53 | C27: 334.57 | D27: 268.19 | E27: 221.84 | F27: 172.02 | G27: 118.7 | H27: 84.07
A28: FOCF Yield
A29: Free Cash Flow Yield - % | B29: 3.08 | C29: 2.71 | D29: 0.82 | E29: 2.42 | F29: 1.33 | G29: 1.23 | H29: 2.64
A30: Free Cash Flow Yield - %, 5 Year Average | B30: 2.18 | C30: 1.82 | D30: 1.6 | E30: 1.92 | F30: 1.79 | G30: 2.03 | H30: 2.49
A31: Dividend Yield
A32: Dividend Yield - Common Stock - Net - Issue Specific - % | B32: 0 | C32: 0 | D32: 0 | E32: 0 | F32: 0 | G32: 0 | H32: 0
A33: Dividend Yield - Common Stock - Net - Issue Specific - %, 5 Year Average | B33: 0 | C33: 0 | D33: 0 | E33: 0 | F33: 0 | G33: 0 | H33: 0
A34: Dividend Yield - Common Stock - Gross - Issue Specific - % | B34: 0 | C34: 0 | D34: 0 | E34: 0 | F34: 0 | G34: 0 | H34: 0
A35: Dividend Yield - Common Stock - Gross - Issue Specific - %, 5 Year Average | B35: 0 | C35: 0 | D35: 0 | E35: 0 | F35: 0 | G35: 0 | H35: 0
A36: Price to Book
A37: Price to Book Value per Share - Issue Specific | B37: 12.11 | C37: 14.84 | D37: 13.07 | E37: 15.42 | F37: 17.41 | G37: 16.75 | H37: 14.17
A38: Price to Book Value per Share - Issue Specific, 5 Year Average | B38: 14.26 | C38: 15.25 | D38: 15.28 | E38: 14.8 | F38: 13.49 | G38: 11.45 | H38: 9.29
A39: Price to Tangible Book
A40: Price to Tangible Book Value per Share | B40: 12.61 | C40: 14.92 | D40: 13.27 | E40: 18.51 | F40: 21.3 | G40: 16.96 | H40: 14.42
A41: Price to Tangible Book Value per Share, 5 Year Average | B41: 15.29 | C41: 16.39 | D41: 16.73 | E41: 16.41 | F41: 14.43 | G41: 11.64 | H41: 9.47
A42: Price to Sales
A43: Price to Revenue from Business Activities - Total per Share | B43: 4.85 | C43: 6.31 | D43: 4.91 | E43: 6.58 | F43: 9.77 | G43: 7.88 | H43: 5.95
A44: Price to Revenue from Business Activities - Total per Share, 5 Year Average | B44: 6.04 | C44: 6.66 | D44: 6.71 | E44: 7.11 | F44: 6.88 | G44: 5.59 | H44: 4.77
A45: Price to FOCF
A46: Price to Free Cash Flow per Share | B46: 32.42 | C46: 36.94 | D46: 121.4 | E46: 41.38 | F46: 74.92 | G46: 81.16 | H46: 37.87
A47: Price to Free Cash Flow per Share, 5 Year Average | B47: 45.85 | C47: 54.9 | D47: 62.69 | E47: 52.17 | F47: 56.02 | G47: 49.2 | H47: 40.17
A48: Price to CF Per Share
A49: Price to Cash Flow per Share | B49: 22.7 | C49: 31.48 | D49: 34.71 | E49: 34.31 | F49: 55.55 | G49: 38.82 | H49: 31.9
A50: Price to Cash Flow per Share, 5 Year Average | B50: 32.13 | C50: 36.82 | D50: 38.5 | E50: 38.25 | F50: 37.99 | G50: 31.01 | H50: 27.96
A51: Price to Diluted EPS
A52: Price to EPS - Diluted - excluding Extraordinary Items Applicable to Common - Total | B52: 28.29 | C52: 39.18 | D52: 46.55 | E52: 42.2 | F52: 73.04 | G52: 48.56 | H52: 39.85
A53: Price to EPS - Diluted - excluding Extraordinary Items Applicable to Common - Total, 5 Year Average | B53: 40.6 | C53: 46.74 | D53: 49.19 | E53: 48.4 | F53: 48.76 | G53: 39.48 | H53: 35.75
A54: Price to Normalized Diluted EPS
A55: Price to EPS - Diluted - excluding Extraordinary Items - Normalized - Total | B55: 28.23 | C55: 37.38 | D55: 31.51 | E55: 40.48 | F55: 69.52 | G55: 48.45 | H55: 39.96
A56: Price to EPS - Diluted - excluding Extraordinary Items - Normalized - Total, 5 Year Average | B56: 14.26 | C56: 15.25 | D56: 15.28 | E56: 14.8 | F56: 13.49 | G56: 11.45 | H56: 9.29
A57: PEG Ratio
A58: PE Growth Ratio | B58: 1.41 | C58: 0.47 | D58: -4.31 | E58: 0.64 | F58: -8.37 | G58: 1.41 | H58: 0.7
A59: PE Growth Ratio, 5 Year Average | B59: 1.67 | C59: 1.72 | D59: 2.1 | E59: 1.75 | F59: 2.57 | G59: 1.62 | H59: 2.57
A60: EV to Sales
A61: Enterprise Value to Revenue from Business Activities - Total | B61: 4.58 | C61: 6.04 | D61: 4.75 | E61: 6.33 | F61: 9.47 | G61: 7.56 | H61: 5.62
A62: Enterprise Value to Revenue from Business Activities - Total, 5 Year Average | B62: 5.81 | C62: 6.43 | D62: 6.47 | E62: 6.78 | F62: 6.5 | G62: 5.22 | H62: 4.4
A63: EV to EBITDA
A64: Enterprise Value to Earnings before Interest, Taxes, Depreciation & Amortization (EBITDA) | B64: 16.4 | C64: 22.46 | D64: 19.09 | E64: 24.76 | F64: 40.27 | G64: 28.6 | H64: 22.33
A65: Enterprise Value to Earnings before Interest, Taxes, Depreciation & Amortization (EBITDA), 5 Year Average | B65: 22.2 | C65: 25.08 | D65: 25.78 | E65: 27.31 | F65: 26.97 | G65: 21.83 | H65: 19.03
A66: EV to CFO
A67: Enterprise Value to Net Cash Flow from Operating Activities | B67: 21.33 | C67: 25.3 | D67: 39.86 | E67: 28.5 | F67: 51.89 | G67: 44.97 | H67: 24.86
A68: Enterprise Value to Net Cash Flow from Operating Activities, 5 Year Average | B68: 29.29 | C68: 33.96 | D68: 36.83 | E68: 34.09 | F68: 35.07 | G68: 28.93 | H68: 23.96
A69: EV to FOCF
A70: Enterprise Value to Free Cash Flow | B70: 30.61 | C70: 35.33 | D70: 117.5 | E70: 39.8 | F70: 72.61 | G70: 77.92 | H70: 35.72
A71: Enterprise Value to Free Cash Flow, 5 Year Average | B71: 44.17 | C71: 52.96 | D71: 60.13 | E71: 49.78 | F71: 52.99 | G71: 46.01 | H71: 37.27

Sheet VALUATION CALC
A1: Firm Valuation | I1: Sites Used
B2: Latest P/E ratio | D2: ADDITIONAL: Latest P/B Ratio | F2: Latest enterprice Value/EBITDA | I2: 1 | J2: https://stockanalysis.com/quote/tyo/7936/statistics/
A3: ASICS | C3: 31.5 | E3: 9.77 | G3: 16.45 | I3: 2 | J3: https://stockanalysis.com/stocks/nke/statistics/
C4: + | E4: + | G4: + | I4: 3 | J4: https://stockanalysis.com/quote/etr/ADS/statistics/
A5: ADIDAS | C5: 22.36 | E5: 4.45 | G5: 10.37
C6: + | E6: + | G6: +
A7: NIKE | C7: 32.24 | E7: 6.89 | G7: 22.71
A9: Competitors Average | C9: =AVERAGE(C3,C5,C7) -> 28.7 | E9: =AVERAGE(E3,E5,E7) -> 7.0366667 | G9: =AVERAGE(G3,G5,G7) -> 16.51
A11: Expected Stock Price | B11: P/E Multiple = | C11: =C39 -> 420.168 | D11: P/B Multiple= | E11: 240.7 | F11: EBITDA Multiple= | G11: =J64 -> 401.66833
A13: NOTE: | B13: Even though the companies report in different currencies, we didn’t need to convert anything because P/E, P/B, and EV/EBITDA are ratio-based. These multiples are naturally currency-neutral
I14: SUMMARY
I15: Company | J15: Current P/E ratio
I16: Lululemon | J16: =D33 -> 28.29235
I17: ASICS | J17: =C3 -> 31.5
I18: ADIDAS | J18: =C5 -> 22.36
I19: NIKE | J19: =C7 -> 32.24
I24: SUMMARY
I25: Company | J25: Current P/B ratio
I26: Lululemon | J26: =D51 -> 12.11
I27: ASICS | J27: =E3 -> 9.77
A28: Price to Earnings Ratio (Lululemon) | I28: ADIDAS | J28: =E5 -> 4.45
A29: Year | B29: Price | C29: Earnings per Share | D29: P/E Ratio | I29: NIKE | J29: =E7 -> 6.89
A30: 2022 | B30: =Valuation!E26 -> 315.91 | C30: =Valuation!E55 -> 40.48 | D30: =B30/C30 -> 7.8041008
A31: 2023 | B31: =Valuation!D26 -> 310.85 | C31: =Valuation!D55 -> 31.51 | D31: =B31/C31 -> 9.8651222
A32: 2024 | B32: =Valuation!C26 -> 478.03 | C32: =Valuation!C55 -> 37.38 | D32: =B32/C32 -> 12.78839
A33: 2025 / Current | B33: =Valuation!B26 -> 414.2 | C33: 14.64 | D33: =B33/C33 -> 28.29235 | E33: ⟵ | F33: =B33/C33'
B34: ↑ | C34: ↑
B35: =Valuation!B26' | C35: ='Financial Summary'!B63'
A37: PE multiple | I37: Method used | J37: Expected Stock Price
A38: Current EPS | B38: Industry Average | C38: Estimated Stock Price
A39: =C33 -> 14.64 | B39: =C9 -> 28.7 | C39: =A39 * B39 -> 420.168 | I39: P/E multiple | J39: =C11 -> 420.168
C40: ↑ | I40: P/B multiple | J40: =E11 -> 240.7
C41: =A37 * B37' | I41: EBITDA multiple | J41: =G11 -> 401.66833
A46: Price to Book Ratio (Lululemon)
A47: Year | B47: Market Price per Share (USD) | C47: Book Value per Share (USD) | D47: P/B Ratio
A48: 2022 | B48: 315.91 | C48: =B48/D48 -> 20.48703 | D48: =Valuation!E37 -> 15.42
A49: 2023 | B49: 310.85 | C49: =B49/D49 -> 23.783474 | D49: =Valuation!D37 -> 13.07
A50: 2024 | B50: 478.03 | C50: =B50/D50 -> 32.212264 | D50: =Valuation!C37 -> 14.84
A51: 2025 / Current | B51: 414.2 | C51: =B51/D51 -> 34.203138 | D51: =Valuation!B37 -> 12.11 | E51: ⟵ | F51: =Valuation!B37'
A53: P/B Multiple
A54: Book Value/ Share = Price / P/B | B54: Average P/B | C54: Estimated Stock Price
A55: =B51/D51 -> 34.203138 | B55: =E9 -> 7.0366667 | C55: =A55*B55 -> 240.67608
A56: ↑ | C56: ↑
A57: =B49/D49' | C57: =A53*B53'
A60: Lululemon EBITDA | F60: EBITDA | G60: EBITDA Multiples | H60: V0
A61: Year | B61: Adjusted EBITDA/($ in millions) | C61: Adjusted EBITDA margin | E61: '=B63' ⟶ | F61: =B65 -> 2955.72 | G61: =G9 -> 16.51 | H61: =F61 * G61 -> 48798.937 | I61: ⟵ | J61: =F59 * G59'
A62: 2022 | B62: ='Financial Summary'!E61 -> 1598.96 | C62: =0.256 -> 0.256 | F62: Stock Price estimation
A63: 2023 | B63: ='Financial Summary'!D61 -> 2017.93 | C63: 0.249 | F63: V0 | G63: Cash | H63: Debt | I63: #Shares | J63: Estimated Stock Price
A64: 2024 | B64: ='Financial Summary'!C61 -> 2586.56 | C64: 0.269 | F64: =H61 -> 48798.937 | G64: ='Financial Summary'!B26 -> 1984.34 | H64: ='Financial Summary'!B29 -> 12.4 | I64: ='Financial Summary'!B64 -> 126.4 | J64: =(F64-H64+G64)/I64 -> 401.66833 | K64: ⟵ | L64: =(F62-H62+G62)/I62'
A65: current | B65: ='Financial Summary'!B61 -> 2955.72 | C65: 0.279 | G65: ↑ | H65: ↑ | I65: ↑
B66: ↑ | C66: ↑ | G66: ='Financial Summary'!B26' | H66: ='Financial Summary'!B29' | I66: ='Financial Summary'!B64'
B67: ='Financial Summary'!B61' | C67: for context only

Sheet DCF

Sheet MULTIPLES

Sheet Operating Metrics
A1: Company Fundamentals - Operating Metrics
A2: Company Name | B2: Lululemon Athletica Inc (LULU.O)
A3: Country of Exchange | B3: United States of America
A4: Country of Headquarters | B4: Canada
A5: TRBC Industry Group | B5: Textiles & Apparel
A6: CF Template | B6: IND
A7: Consolidation Basis | B7: Consolidated
A8: Scaling | B8: Millions
A9: Period | B9: Annual
A10: Measure system | B10: Metric
A11: Statement Data | B11: 2025 | C11: 2024 | D11: 2023 | E11: 2022 | F11: 2021 | G11: 2020 | H11: 2019
A12: Period End Date | B12: 45690 | C12: 45319 | D12: 44955 | E12: 44591 | F12: 44227 | G12: 43863 | H12: 43499
A13: Statement Date | B13: 45690 | C13: 45319 | D13: 44955 | E13: 44591 | F13: 44227 | G13: 43863 | H13: 43499
A14: Standardized Currency | B14: USD | C14: USD | D14: USD | E14: USD | F14: USD | G14: USD | H14: USD
A15: Template Type | B15: Industrial | C15: Industrial | D15: Industrial | E15: Industrial | F15: Industrial | G15: Industrial | H15: Industrial
A17: Operating Metrics - Standardized (Currency: Standardized)
A18: Field Name | B18: 02-02-2025 | C18: 28-01-2024 | D18: 29-01-2023 | E18: 30-01-2022 | F18: 31-01-2021 | G18: 02-02-2020 | H18: 03-02-2019
A19: Other Retail Measures
A20: Sales per Unit - Average - Total | H20: 146.69
A21: Comparable Store Sales (Growth %)
A22: Comparable Store Sales Growth Rate - Retail - Total - % | B22: 4 | C22: 8 | D22: 19 | G22: 9 | H22: 7
A23: Comparable Store Sales - Total - Retail | H23: 105452000
A24: Other Retail Measures
A25: Merchandise Margins - Total - % | B25: 59.2 | C25: 58.3 | D25: 55.4 | E25: 57.7 | F25: 56 | G25: 55.9 | H25: 55.2
A26: Stores Number
A27: Stores Closed - Number - Total | B27: 9 | C27: 7 | D27: 6 | E27: 3 | F27: 10 | G27: 6 | H27: 3
A28: Stores Opened - Number - Total | B28: 56 | C28: 56 | D28: 87 | E28: 56 | F28: 40 | G28: 57 | H28: 39
A29: Stores - End of Period - Number - Total | B29: 767 | C29: 711 | D29: 655 | E29: 574 | F29: 521 | G29: 491 | H29: 440
A30: Revenues
A31: Online Sales - Total | B31: 4570446000 | C31: 4311110000 | D31: 3699791000 | E31: 2777944000 | F31: 2284068000 | G31: 1137822000 | H31: 858856000
A32: Retail Sales - Total | B32: 5007872000 | C32: 4410956000 | D32: 3648127000 | E32: 2821497000 | F32: 1658807000 | G32: 2501067000 | H32: 2126363000
A33: Selling Space
A34: Selling Space - Gross - Total | B34: 313269.05 | C34: 275643.32 | D34: 239225.33 | E34: 197418.96 | F34: 172613.85 | G34: 156077.11 | H34: 132479.74
